{
  "@context": "http://iiif.io/api/presentation/2/context.json",
  "@id": "https://digirati-co-uk.github.io/ida-exported-data/iiif/annotations/_roll_M-1011_088_cvs-426-514/ocr_5a6a04ec-3981-474f-9f93-d8688d2cb1c8/annotations.json",
  "@type": "sc:AnnotationList",
  "resources": [
    {
      "@id": "https://elucidate.dlcs-ida.org/anno/b9ed59e7fc986aedaba566bf1bb9a6ce/0",
      "@type": "oa:Annotation",
      "motivation": "sc:painting",
      "on": "https://presley.dlcs-ida.org/iiif/idatest01/_roll_M-1011_088_cvs-426-514/canvas/c463#xywh=253,272,3,39",
      "resource": {
        "@type": "cnt:ContentAsText",
        "chars": "1 ",
        "format": "text/plain"
      }
    },
    {
      "@id": "https://elucidate.dlcs-ida.org/anno/b9ed59e7fc986aedaba566bf1bb9a6ce/1",
      "@type": "oa:Annotation",
      "motivation": "sc:painting",
      "on": "https://presley.dlcs-ida.org/iiif/idatest01/_roll_M-1011_088_cvs-426-514/canvas/c463#xywh=1045,360,98,50",
      "resource": {
        "@type": "cnt:ContentAsText",
        "chars": "( 21) ",
        "format": "text/plain"
      }
    },
    {
      "@id": "https://elucidate.dlcs-ida.org/anno/b9ed59e7fc986aedaba566bf1bb9a6ce/2",
      "@type": "oa:Annotation",
      "motivation": "sc:painting",
      "on": "https://presley.dlcs-ida.org/iiif/idatest01/_roll_M-1011_088_cvs-426-514/canvas/c463#xywh=185,618,1826,53",
      "resource": {
        "@type": "cnt:ContentAsText",
        "chars": "1915 a group of small buildings to serve as a tuberculosis sana tartum, ",
        "format": "text/plain"
      }
    },
    {
      "@id": "https://elucidate.dlcs-ida.org/anno/b9ed59e7fc986aedaba566bf1bb9a6ce/3",
      "@type": "oa:Annotation",
      "motivation": "sc:painting",
      "on": "https://presley.dlcs-ida.org/iiif/idatest01/_roll_M-1011_088_cvs-426-514/canvas/c463#xywh=184,711,1704,46",
      "resource": {
        "@type": "cnt:ContentAsText",
        "chars": "and to attend the needs of such point a fourth physician has been ",
        "format": "text/plain"
      }
    },
    {
      "@id": "https://elucidate.dlcs-ida.org/anno/b9ed59e7fc986aedaba566bf1bb9a6ce/4",
      "@type": "oa:Annotation",
      "motivation": "sc:painting",
      "on": "https://presley.dlcs-ida.org/iiif/idatest01/_roll_M-1011_088_cvs-426-514/canvas/c463#xywh=185,803,252,50",
      "resource": {
        "@type": "cnt:ContentAsText",
        "chars": "requested. ",
        "format": "text/plain"
      }
    },
    {
      "@id": "https://elucidate.dlcs-ida.org/anno/b9ed59e7fc986aedaba566bf1bb9a6ce/5",
      "@type": "oa:Annotation",
      "motivation": "sc:painting",
      "on": "https://presley.dlcs-ida.org/iiif/idatest01/_roll_M-1011_088_cvs-426-514/canvas/c463#xywh=527,800,1439,47",
      "resource": {
        "@type": "cnt:ContentAsText",
        "chars": "It is thought that wherever such station is placed, the ",
        "format": "text/plain"
      }
    },
    {
      "@id": "https://elucidate.dlcs-ida.org/anno/b9ed59e7fc986aedaba566bf1bb9a6ce/6",
      "@type": "oa:Annotation",
      "motivation": "sc:painting",
      "on": "https://presley.dlcs-ida.org/iiif/idatest01/_roll_M-1011_088_cvs-426-514/canvas/c463#xywh=194,886,1772,47",
      "resource": {
        "@type": "cnt:ContentAsText",
        "chars": "loca tion will be favorable as a farmor, district, and that the wifo ",
        "format": "text/plain"
      }
    },
    {
      "@id": "https://elucidate.dlcs-ida.org/anno/b9ed59e7fc986aedaba566bf1bb9a6ce/7",
      "@type": "oa:Annotation",
      "motivation": "sc:painting",
      "on": "https://presley.dlcs-ida.org/iiif/idatest01/_roll_M-1011_088_cvs-426-514/canvas/c463#xywh=188,980,1065,49",
      "resource": {
        "@type": "cnt:ContentAsText",
        "chars": "of such fermer may be appointed as nurse. ",
        "format": "text/plain"
      }
    },
    {
      "@id": "https://elucidate.dlcs-ida.org/anno/b9ed59e7fc986aedaba566bf1bb9a6ce/8",
      "@type": "oa:Annotation",
      "motivation": "sc:painting",
      "on": "https://presley.dlcs-ida.org/iiif/idatest01/_roll_M-1011_088_cvs-426-514/canvas/c463#xywh=1341,974,627,49",
      "resource": {
        "@type": "cnt:ContentAsText",
        "chars": "It is believed that many ",
        "format": "text/plain"
      }
    },
    {
      "@id": "https://elucidate.dlcs-ida.org/anno/b9ed59e7fc986aedaba566bf1bb9a6ce/9",
      "@type": "oa:Annotation",
      "motivation": "sc:painting",
      "on": "https://presley.dlcs-ida.org/iiif/idatest01/_roll_M-1011_088_cvs-426-514/canvas/c463#xywh=191,1062,1745,42",
      "resource": {
        "@type": "cnt:ContentAsText",
        "chars": "Indians could be treated at such a point within the reservation who ",
        "format": "text/plain"
      }
    },
    {
      "@id": "https://elucidate.dlcs-ida.org/anno/b9ed59e7fc986aedaba566bf1bb9a6ce/10",
      "@type": "oa:Annotation",
      "motivation": "sc:painting",
      "on": "https://presley.dlcs-ida.org/iiif/idatest01/_roll_M-1011_088_cvs-426-514/canvas/c463#xywh=189,1150,1616,44",
      "resource": {
        "@type": "cnt:ContentAsText",
        "chars": "would not consent to their transfer to the Phoonix sana tartum. ",
        "format": "text/plain"
      }
    },
    {
      "@id": "https://elucidate.dlcs-ida.org/anno/b9ed59e7fc986aedaba566bf1bb9a6ce/11",
      "@type": "oa:Annotation",
      "motivation": "sc:painting",
      "on": "https://presley.dlcs-ida.org/iiif/idatest01/_roll_M-1011_088_cvs-426-514/canvas/c463#xywh=587,1328,779,52",
      "resource": {
        "@type": "cnt:ContentAsText",
        "chars": "Imrovements made during 1914. ",
        "format": "text/plain"
      }
    },
    {
      "@id": "https://elucidate.dlcs-ida.org/anno/b9ed59e7fc986aedaba566bf1bb9a6ce/12",
      "@type": "oa:Annotation",
      "motivation": "sc:painting",
      "on": "https://presley.dlcs-ida.org/iiif/idatest01/_roll_M-1011_088_cvs-426-514/canvas/c463#xywh=614,1381,594,56",
      "resource": {
        "@type": "cnt:ContentAsText",
        "chars": "( all open market work). ",
        "format": "text/plain"
      }
    },
    {
      "@id": "https://elucidate.dlcs-ida.org/anno/b9ed59e7fc986aedaba566bf1bb9a6ce/13",
      "@type": "oa:Annotation",
      "motivation": "sc:painting",
      "on": "https://presley.dlcs-ida.org/iiif/idatest01/_roll_M-1011_088_cvs-426-514/canvas/c463#xywh=1457,1365,643,52",
      "resource": {
        "@type": "cnt:ContentAsText",
        "chars": "goo Report of Buildings). ",
        "format": "text/plain"
      }
    },
    {
      "@id": "https://elucidate.dlcs-ida.org/anno/b9ed59e7fc986aedaba566bf1bb9a6ce/14",
      "@type": "oa:Annotation",
      "motivation": "sc:painting",
      "on": "https://presley.dlcs-ida.org/iiif/idatest01/_roll_M-1011_088_cvs-426-514/canvas/c463#xywh=1030,1507,311,43",
      "resource": {
        "@type": "cnt:ContentAsText",
        "chars": "Floor Spaco. ",
        "format": "text/plain"
      }
    },
    {
      "@id": "https://elucidate.dlcs-ida.org/anno/b9ed59e7fc986aedaba566bf1bb9a6ce/15",
      "@type": "oa:Annotation",
      "motivation": "sc:painting",
      "on": "https://presley.dlcs-ida.org/iiif/idatest01/_roll_M-1011_088_cvs-426-514/canvas/c463#xywh=1583,1500,381,39",
      "resource": {
        "@type": "cnt:ContentAsText",
        "chars": "Estimated cost. ",
        "format": "text/plain"
      }
    },
    {
      "@id": "https://elucidate.dlcs-ida.org/anno/b9ed59e7fc986aedaba566bf1bb9a6ce/16",
      "@type": "oa:Annotation",
      "motivation": "sc:painting",
      "on": "https://presley.dlcs-ida.org/iiif/idatest01/_roll_M-1011_088_cvs-426-514/canvas/c463#xywh=198,1596,575,43",
      "resource": {
        "@type": "cnt:ContentAsText",
        "chars": "Woqui Indian Hospital: ",
        "format": "text/plain"
      }
    },
    {
      "@id": "https://elucidate.dlcs-ida.org/anno/b9ed59e7fc986aedaba566bf1bb9a6ce/17",
      "@type": "oa:Annotation",
      "motivation": "sc:painting",
      "on": "https://presley.dlcs-ida.org/iiif/idatest01/_roll_M-1011_088_cvs-426-514/canvas/c463#xywh=1083,1592,332,47",
      "resource": {
        "@type": "cnt:ContentAsText",
        "chars": "4,000 squ.ft. ",
        "format": "text/plain"
      }
    },
    {
      "@id": "https://elucidate.dlcs-ida.org/anno/b9ed59e7fc986aedaba566bf1bb9a6ce/18",
      "@type": "oa:Annotation",
      "motivation": "sc:painting",
      "on": "https://presley.dlcs-ida.org/iiif/idatest01/_roll_M-1011_088_cvs-426-514/canvas/c463#xywh=1661,1580,227,53",
      "resource": {
        "@type": "cnt:ContentAsText",
        "chars": "$ 13,600. ",
        "format": "text/plain"
      }
    },
    {
      "@id": "https://elucidate.dlcs-ida.org/anno/b9ed59e7fc986aedaba566bf1bb9a6ce/19",
      "@type": "oa:Annotation",
      "motivation": "sc:painting",
      "on": "https://presley.dlcs-ida.org/iiif/idatest01/_roll_M-1011_088_cvs-426-514/canvas/c463#xywh=199,1680,674,51",
      "resource": {
        "@type": "cnt:ContentAsText",
        "chars": "Domostio Scionco Building: ",
        "format": "text/plain"
      }
    },
    {
      "@id": "https://elucidate.dlcs-ida.org/anno/b9ed59e7fc986aedaba566bf1bb9a6ce/20",
      "@type": "oa:Annotation",
      "motivation": "sc:painting",
      "on": "https://presley.dlcs-ida.org/iiif/idatest01/_roll_M-1011_088_cvs-426-514/canvas/c463#xywh=1084,1679,134,53",
      "resource": {
        "@type": "cnt:ContentAsText",
        "chars": "1,500 ",
        "format": "text/plain"
      }
    },
    {
      "@id": "https://elucidate.dlcs-ida.org/anno/b9ed59e7fc986aedaba566bf1bb9a6ce/21",
      "@type": "oa:Annotation",
      "motivation": "sc:painting",
      "on": "https://presley.dlcs-ida.org/iiif/idatest01/_roll_M-1011_088_cvs-426-514/canvas/c463#xywh=1740,1677,151,50",
      "resource": {
        "@type": "cnt:ContentAsText",
        "chars": "2,200. ",
        "format": "text/plain"
      }
    },
    {
      "@id": "https://elucidate.dlcs-ida.org/anno/b9ed59e7fc986aedaba566bf1bb9a6ce/22",
      "@type": "oa:Annotation",
      "motivation": "sc:painting",
      "on": "https://presley.dlcs-ida.org/iiif/idatest01/_roll_M-1011_088_cvs-426-514/canvas/c463#xywh=202,1771,725,51",
      "resource": {
        "@type": "cnt:ContentAsText",
        "chars": "Polacca Day School Building: ",
        "format": "text/plain"
      }
    },
    {
      "@id": "https://elucidate.dlcs-ida.org/anno/b9ed59e7fc986aedaba566bf1bb9a6ce/23",
      "@type": "oa:Annotation",
      "motivation": "sc:painting",
      "on": "https://presley.dlcs-ida.org/iiif/idatest01/_roll_M-1011_088_cvs-426-514/canvas/c463#xywh=1087,1768,130,51",
      "resource": {
        "@type": "cnt:ContentAsText",
        "chars": "2,000 ",
        "format": "text/plain"
      }
    },
    {
      "@id": "https://elucidate.dlcs-ida.org/anno/b9ed59e7fc986aedaba566bf1bb9a6ce/24",
      "@type": "oa:Annotation",
      "motivation": "sc:painting",
      "on": "https://presley.dlcs-ida.org/iiif/idatest01/_roll_M-1011_088_cvs-426-514/canvas/c463#xywh=1743,1763,146,48",
      "resource": {
        "@type": "cnt:ContentAsText",
        "chars": "1,800. ",
        "format": "text/plain"
      }
    },
    {
      "@id": "https://elucidate.dlcs-ida.org/anno/b9ed59e7fc986aedaba566bf1bb9a6ce/25",
      "@type": "oa:Annotation",
      "motivation": "sc:painting",
      "on": "https://presley.dlcs-ida.org/iiif/idatest01/_roll_M-1011_088_cvs-426-514/canvas/c463#xywh=199,1859,784,48",
      "resource": {
        "@type": "cnt:ContentAsText",
        "chars": "Doctor's Cottago, Socond Noga: ",
        "format": "text/plain"
      }
    },
    {
      "@id": "https://elucidate.dlcs-ida.org/anno/b9ed59e7fc986aedaba566bf1bb9a6ce/26",
      "@type": "oa:Annotation",
      "motivation": "sc:painting",
      "on": "https://presley.dlcs-ida.org/iiif/idatest01/_roll_M-1011_088_cvs-426-514/canvas/c463#xywh=1141,1856,78,36",
      "resource": {
        "@type": "cnt:ContentAsText",
        "chars": "700 ",
        "format": "text/plain"
      }
    },
    {
      "@id": "https://elucidate.dlcs-ida.org/anno/b9ed59e7fc986aedaba566bf1bb9a6ce/27",
      "@type": "oa:Annotation",
      "motivation": "sc:painting",
      "on": "https://presley.dlcs-ida.org/iiif/idatest01/_roll_M-1011_088_cvs-426-514/canvas/c463#xywh=1744,1852,146,49",
      "resource": {
        "@type": "cnt:ContentAsText",
        "chars": "1,200. ",
        "format": "text/plain"
      }
    },
    {
      "@id": "https://elucidate.dlcs-ida.org/anno/b9ed59e7fc986aedaba566bf1bb9a6ce/28",
      "@type": "oa:Annotation",
      "motivation": "sc:painting",
      "on": "https://presley.dlcs-ida.org/iiif/idatest01/_roll_M-1011_088_cvs-426-514/canvas/c463#xywh=206,1950,462,45",
      "resource": {
        "@type": "cnt:ContentAsText",
        "chars": "Chimopowy Laundry: ",
        "format": "text/plain"
      }
    },
    {
      "@id": "https://elucidate.dlcs-ida.org/anno/b9ed59e7fc986aedaba566bf1bb9a6ce/29",
      "@type": "oa:Annotation",
      "motivation": "sc:painting",
      "on": "https://presley.dlcs-ida.org/iiif/idatest01/_roll_M-1011_088_cvs-426-514/canvas/c463#xywh=1143,1945,77,42",
      "resource": {
        "@type": "cnt:ContentAsText",
        "chars": "540 ",
        "format": "text/plain"
      }
    },
    {
      "@id": "https://elucidate.dlcs-ida.org/anno/b9ed59e7fc986aedaba566bf1bb9a6ce/30",
      "@type": "oa:Annotation",
      "motivation": "sc:painting",
      "on": "https://presley.dlcs-ida.org/iiif/idatest01/_roll_M-1011_088_cvs-426-514/canvas/c463#xywh=1797,1939,96,40",
      "resource": {
        "@type": "cnt:ContentAsText",
        "chars": "950. ",
        "format": "text/plain"
      }
    },
    {
      "@id": "https://elucidate.dlcs-ida.org/anno/b9ed59e7fc986aedaba566bf1bb9a6ce/31",
      "@type": "oa:Annotation",
      "motivation": "sc:painting",
      "on": "https://presley.dlcs-ida.org/iiif/idatest01/_roll_M-1011_088_cvs-426-514/canvas/c463#xywh=202,2031,622,55",
      "resource": {
        "@type": "cnt:ContentAsText",
        "chars": "Barn, Oraibi Day School: ",
        "format": "text/plain"
      }
    },
    {
      "@id": "https://elucidate.dlcs-ida.org/anno/b9ed59e7fc986aedaba566bf1bb9a6ce/32",
      "@type": "oa:Annotation",
      "motivation": "sc:painting",
      "on": "https://presley.dlcs-ida.org/iiif/idatest01/_roll_M-1011_088_cvs-426-514/canvas/c463#xywh=1089,2027,132,52",
      "resource": {
        "@type": "cnt:ContentAsText",
        "chars": "1,089 ",
        "format": "text/plain"
      }
    },
    {
      "@id": "https://elucidate.dlcs-ida.org/anno/b9ed59e7fc986aedaba566bf1bb9a6ce/33",
      "@type": "oa:Annotation",
      "motivation": "sc:painting",
      "on": "https://presley.dlcs-ida.org/iiif/idatest01/_roll_M-1011_088_cvs-426-514/canvas/c463#xywh=1745,2024,151,50",
      "resource": {
        "@type": "cnt:ContentAsText",
        "chars": "1,200. ",
        "format": "text/plain"
      }
    },
    {
      "@id": "https://elucidate.dlcs-ida.org/anno/b9ed59e7fc986aedaba566bf1bb9a6ce/34",
      "@type": "oa:Annotation",
      "motivation": "sc:painting",
      "on": "https://presley.dlcs-ida.org/iiif/idatest01/_roll_M-1011_088_cvs-426-514/canvas/c463#xywh=207,2121,489,56",
      "resource": {
        "@type": "cnt:ContentAsText",
        "chars": "Barn, Topo srrings: ",
        "format": "text/plain"
      }
    },
    {
      "@id": "https://elucidate.dlcs-ida.org/anno/b9ed59e7fc986aedaba566bf1bb9a6ce/35",
      "@type": "oa:Annotation",
      "motivation": "sc:painting",
      "on": "https://presley.dlcs-ida.org/iiif/idatest01/_roll_M-1011_088_cvs-426-514/canvas/c463#xywh=1145,2122,79,39",
      "resource": {
        "@type": "cnt:ContentAsText",
        "chars": "432 ",
        "format": "text/plain"
      }
    },
    {
      "@id": "https://elucidate.dlcs-ida.org/anno/b9ed59e7fc986aedaba566bf1bb9a6ce/36",
      "@type": "oa:Annotation",
      "motivation": "sc:painting",
      "on": "https://presley.dlcs-ida.org/iiif/idatest01/_roll_M-1011_088_cvs-426-514/canvas/c463#xywh=1282,2030,18,122",
      "resource": {
        "@type": "cnt:ContentAsText",
        "chars": ": ",
        "format": "text/plain"
      }
    },
    {
      "@id": "https://elucidate.dlcs-ida.org/anno/b9ed59e7fc986aedaba566bf1bb9a6ce/37",
      "@type": "oa:Annotation",
      "motivation": "sc:painting",
      "on": "https://presley.dlcs-ida.org/iiif/idatest01/_roll_M-1011_088_cvs-426-514/canvas/c463#xywh=1283,2112,19,130",
      "resource": {
        "@type": "cnt:ContentAsText",
        "chars": ": ",
        "format": "text/plain"
      }
    },
    {
      "@id": "https://elucidate.dlcs-ida.org/anno/b9ed59e7fc986aedaba566bf1bb9a6ce/38",
      "@type": "oa:Annotation",
      "motivation": "sc:painting",
      "on": "https://presley.dlcs-ida.org/iiif/idatest01/_roll_M-1011_088_cvs-426-514/canvas/c463#xywh=1802,2115,94,41",
      "resource": {
        "@type": "cnt:ContentAsText",
        "chars": "300. ",
        "format": "text/plain"
      }
    },
    {
      "@id": "https://elucidate.dlcs-ida.org/anno/b9ed59e7fc986aedaba566bf1bb9a6ce/39",
      "@type": "oa:Annotation",
      "motivation": "sc:painting",
      "on": "https://presley.dlcs-ida.org/iiif/idatest01/_roll_M-1011_088_cvs-426-514/canvas/c463#xywh=217,2208,714,54",
      "resource": {
        "@type": "cnt:ContentAsText",
        "chars": "Dynamite House, Koams Canon: ",
        "format": "text/plain"
      }
    },
    {
      "@id": "https://elucidate.dlcs-ida.org/anno/b9ed59e7fc986aedaba566bf1bb9a6ce/40",
      "@type": "oa:Annotation",
      "motivation": "sc:painting",
      "on": "https://presley.dlcs-ida.org/iiif/idatest01/_roll_M-1011_088_cvs-426-514/canvas/c463#xywh=1171,2210,52,34",
      "resource": {
        "@type": "cnt:ContentAsText",
        "chars": "50 ",
        "format": "text/plain"
      }
    },
    {
      "@id": "https://elucidate.dlcs-ida.org/anno/b9ed59e7fc986aedaba566bf1bb9a6ce/41",
      "@type": "oa:Annotation",
      "motivation": "sc:painting",
      "on": "https://presley.dlcs-ida.org/iiif/idatest01/_roll_M-1011_088_cvs-426-514/canvas/c463#xywh=1803,2202,93,39",
      "resource": {
        "@type": "cnt:ContentAsText",
        "chars": "100. ",
        "format": "text/plain"
      }
    },
    {
      "@id": "https://elucidate.dlcs-ida.org/anno/b9ed59e7fc986aedaba566bf1bb9a6ce/42",
      "@type": "oa:Annotation",
      "motivation": "sc:painting",
      "on": "https://presley.dlcs-ida.org/iiif/idatest01/_roll_M-1011_088_cvs-426-514/canvas/c463#xywh=213,2298,637,46",
      "resource": {
        "@type": "cnt:ContentAsText",
        "chars": "sop tio Tark, Keams Canon: ",
        "format": "text/plain"
      }
    },
    {
      "@id": "https://elucidate.dlcs-ida.org/anno/b9ed59e7fc986aedaba566bf1bb9a6ce/43",
      "@type": "oa:Annotation",
      "motivation": "sc:painting",
      "on": "https://presley.dlcs-ida.org/iiif/idatest01/_roll_M-1011_088_cvs-426-514/canvas/c463#xywh=1802,2290,97,39",
      "resource": {
        "@type": "cnt:ContentAsText",
        "chars": "785. ",
        "format": "text/plain"
      }
    },
    {
      "@id": "https://elucidate.dlcs-ida.org/anno/b9ed59e7fc986aedaba566bf1bb9a6ce/44",
      "@type": "oa:Annotation",
      "motivation": "sc:painting",
      "on": "https://presley.dlcs-ida.org/iiif/idatest01/_roll_M-1011_088_cvs-426-514/canvas/c463#xywh=1672,2371,227,54",
      "resource": {
        "@type": "cnt:ContentAsText",
        "chars": "$ 22,075. ",
        "format": "text/plain"
      }
    },
    {
      "@id": "https://elucidate.dlcs-ida.org/anno/b9ed59e7fc986aedaba566bf1bb9a6ce/45",
      "@type": "oa:Annotation",
      "motivation": "sc:painting",
      "on": "https://presley.dlcs-ida.org/iiif/idatest01/_roll_M-1011_088_cvs-426-514/canvas/c463#xywh=343,2472,1562,62",
      "resource": {
        "@type": "cnt:ContentAsText",
        "chars": "Had it been possible to find water for the farmer's station, ",
        "format": "text/plain"
      }
    },
    {
      "@id": "https://elucidate.dlcs-ida.org/anno/b9ed59e7fc986aedaba566bf1bb9a6ce/46",
      "@type": "oa:Annotation",
      "motivation": "sc:painting",
      "on": "https://presley.dlcs-ida.org/iiif/idatest01/_roll_M-1011_088_cvs-426-514/canvas/c463#xywh=342,2515,1575,66",
      "resource": {
        "@type": "cnt:ContentAsText",
        "chars": "and had not plans' so changed as to delay the construction of ",
        "format": "text/plain"
      }
    },
    {
      "@id": "https://elucidate.dlcs-ida.org/anno/b9ed59e7fc986aedaba566bf1bb9a6ce/47",
      "@type": "oa:Annotation",
      "motivation": "sc:painting",
      "on": "https://presley.dlcs-ida.org/iiif/idatest01/_roll_M-1011_088_cvs-426-514/canvas/c463#xywh=347,2560,1565,62",
      "resource": {
        "@type": "cnt:ContentAsText",
        "chars": "the field matron's station, all proviously outlined improvo ",
        "format": "text/plain"
      }
    },
    {
      "@id": "https://elucidate.dlcs-ida.org/anno/b9ed59e7fc986aedaba566bf1bb9a6ce/48",
      "@type": "oa:Annotation",
      "motivation": "sc:painting",
      "on": "https://presley.dlcs-ida.org/iiif/idatest01/_roll_M-1011_088_cvs-426-514/canvas/c463#xywh=343,2606,1597,61",
      "resource": {
        "@type": "cnt:ContentAsText",
        "chars": "ments for 1914 would have been completed within the year, and ",
        "format": "text/plain"
      }
    },
    {
      "@id": "https://elucidate.dlcs-ida.org/anno/b9ed59e7fc986aedaba566bf1bb9a6ce/49",
      "@type": "oa:Annotation",
      "motivation": "sc:painting",
      "on": "https://presley.dlcs-ida.org/iiif/idatest01/_roll_M-1011_088_cvs-426-514/canvas/c463#xywh=347,2654,1586,54",
      "resource": {
        "@type": "cnt:ContentAsText",
        "chars": "in the open market, thanks to an excellent corps of employ es. ",
        "format": "text/plain"
      }
    },
    {
      "@id": "https://elucidate.dlcs-ida.org/anno/b9ed59e7fc986aedaba566bf1bb9a6ce/50",
      "@type": "oa:Annotation",
      "motivation": "sc:painting",
      "on": "https://presley.dlcs-ida.org/iiif/idatest01/_roll_M-1011_088_cvs-426-514/canvas/c463#xywh=341,2696,1625,55",
      "resource": {
        "@type": "cnt:ContentAsText",
        "chars": "Four of these mechanios have been lost to 1915, either through ",
        "format": "text/plain"
      }
    },
    {
      "@id": "https://elucidate.dlcs-ida.org/anno/b9ed59e7fc986aedaba566bf1bb9a6ce/51",
      "@type": "oa:Annotation",
      "motivation": "sc:painting",
      "on": "https://presley.dlcs-ida.org/iiif/idatest01/_roll_M-1011_088_cvs-426-514/canvas/c463#xywh=351,2736,1539,61",
      "resource": {
        "@type": "cnt:ContentAsText",
        "chars": "transfer or resignation. It is thought that$ 50,000 would ",
        "format": "text/plain"
      }
    },
    {
      "@id": "https://elucidate.dlcs-ida.org/anno/b9ed59e7fc986aedaba566bf1bb9a6ce/52",
      "@type": "oa:Annotation",
      "motivation": "sc:painting",
      "on": "https://presley.dlcs-ida.org/iiif/idatest01/_roll_M-1011_088_cvs-426-514/canvas/c463#xywh=345,2779,1615,61",
      "resource": {
        "@type": "cnt:ContentAsText",
        "chars": "be necessary to procur. the above improvements under contract. ",
        "format": "text/plain"
      }
    }
  ]
}