{
  "@context": "http://iiif.io/api/presentation/2/context.json",
  "@id": "https://digirati-co-uk.github.io/ida-exported-data/iiif/annotations/_roll_M-1070_01_cvs-131-367/ocr_a1caca63-744b-4e5e-bf10-d6b80123f232/annotations.json",
  "@type": "sc:AnnotationList",
  "resources": [
    {
      "@id": "https://elucidate.dlcs-ida.org/anno/faa476750615e2ef2331452711704c5d/0",
      "@type": "oa:Annotation",
      "motivation": "sc:painting",
      "on": "https://presley.dlcs-ida.org/iiif/idatest01/_roll_M-1070_01_cvs-131-367/canvas/c252#xywh=1339,497,64,161",
      "resource": {
        "@type": "cnt:ContentAsText",
        "chars": ", ",
        "format": "text/plain"
      }
    },
    {
      "@id": "https://elucidate.dlcs-ida.org/anno/faa476750615e2ef2331452711704c5d/1",
      "@type": "oa:Annotation",
      "motivation": "sc:painting",
      "on": "https://presley.dlcs-ida.org/iiif/idatest01/_roll_M-1070_01_cvs-131-367/canvas/c252#xywh=496,584,764,80",
      "resource": {
        "@type": "cnt:ContentAsText",
        "chars": "A hoto, side at that ",
        "format": "text/plain"
      }
    },
    {
      "@id": "https://elucidate.dlcs-ida.org/anno/faa476750615e2ef2331452711704c5d/2",
      "@type": "oa:Annotation",
      "motivation": "sc:painting",
      "on": "https://presley.dlcs-ida.org/iiif/idatest01/_roll_M-1070_01_cvs-131-367/canvas/c252#xywh=1315,621,511,85",
      "resource": {
        "@type": "cnt:ContentAsText",
        "chars": "arguogus trees ",
        "format": "text/plain"
      }
    },
    {
      "@id": "https://elucidate.dlcs-ida.org/anno/faa476750615e2ef2331452711704c5d/3",
      "@type": "oa:Annotation",
      "motivation": "sc:painting",
      "on": "https://presley.dlcs-ida.org/iiif/idatest01/_roll_M-1070_01_cvs-131-367/canvas/c252#xywh=446,680,900,99",
      "resource": {
        "@type": "cnt:ContentAsText",
        "chars": "Yoder. a ne, the hang ocease ",
        "format": "text/plain"
      }
    },
    {
      "@id": "https://elucidate.dlcs-ida.org/anno/faa476750615e2ef2331452711704c5d/4",
      "@type": "oa:Annotation",
      "motivation": "sc:painting",
      "on": "https://presley.dlcs-ida.org/iiif/idatest01/_roll_M-1070_01_cvs-131-367/canvas/c252#xywh=1422,703,413,46",
      "resource": {
        "@type": "cnt:ContentAsText",
        "chars": "Screw, Sas ",
        "format": "text/plain"
      }
    },
    {
      "@id": "https://elucidate.dlcs-ida.org/anno/faa476750615e2ef2331452711704c5d/5",
      "@type": "oa:Annotation",
      "motivation": "sc:painting",
      "on": "https://presley.dlcs-ida.org/iiif/idatest01/_roll_M-1070_01_cvs-131-367/canvas/c252#xywh=443,762,662,63",
      "resource": {
        "@type": "cnt:ContentAsText",
        "chars": "| the accusers to levee ",
        "format": "text/plain"
      }
    },
    {
      "@id": "https://elucidate.dlcs-ida.org/anno/faa476750615e2ef2331452711704c5d/6",
      "@type": "oa:Annotation",
      "motivation": "sc:painting",
      "on": "https://presley.dlcs-ida.org/iiif/idatest01/_roll_M-1070_01_cvs-131-367/canvas/c252#xywh=1205,785,371,73",
      "resource": {
        "@type": "cnt:ContentAsText",
        "chars": "Focus is ae ",
        "format": "text/plain"
      }
    },
    {
      "@id": "https://elucidate.dlcs-ida.org/anno/faa476750615e2ef2331452711704c5d/7",
      "@type": "oa:Annotation",
      "motivation": "sc:painting",
      "on": "https://presley.dlcs-ida.org/iiif/idatest01/_roll_M-1070_01_cvs-131-367/canvas/c252#xywh=1623,799,126,38",
      "resource": {
        "@type": "cnt:ContentAsText",
        "chars": "are ",
        "format": "text/plain"
      }
    },
    {
      "@id": "https://elucidate.dlcs-ida.org/anno/faa476750615e2ef2331452711704c5d/8",
      "@type": "oa:Annotation",
      "motivation": "sc:painting",
      "on": "https://presley.dlcs-ida.org/iiif/idatest01/_roll_M-1070_01_cvs-131-367/canvas/c252#xywh=492,844,1273,89",
      "resource": {
        "@type": "cnt:ContentAsText",
        "chars": "hereoftheast oе Aters, upon his alia, ",
        "format": "text/plain"
      }
    },
    {
      "@id": "https://elucidate.dlcs-ida.org/anno/faa476750615e2ef2331452711704c5d/9",
      "@type": "oa:Annotation",
      "motivation": "sc:painting",
      "on": "https://presley.dlcs-ida.org/iiif/idatest01/_roll_M-1070_01_cvs-131-367/canvas/c252#xywh=619,950,380,50",
      "resource": {
        "@type": "cnt:ContentAsText",
        "chars": "ea ace a day ",
        "format": "text/plain"
      }
    },
    {
      "@id": "https://elucidate.dlcs-ida.org/anno/faa476750615e2ef2331452711704c5d/10",
      "@type": "oa:Annotation",
      "motivation": "sc:painting",
      "on": "https://presley.dlcs-ida.org/iiif/idatest01/_roll_M-1070_01_cvs-131-367/canvas/c252#xywh=1021,951,638,49",
      "resource": {
        "@type": "cnt:ContentAsText",
        "chars": "9, an an e- ch; ",
        "format": "text/plain"
      }
    },
    {
      "@id": "https://elucidate.dlcs-ida.org/anno/faa476750615e2ef2331452711704c5d/11",
      "@type": "oa:Annotation",
      "motivation": "sc:painting",
      "on": "https://presley.dlcs-ida.org/iiif/idatest01/_roll_M-1070_01_cvs-131-367/canvas/c252#xywh=489,1011,182,56",
      "resource": {
        "@type": "cnt:ContentAsText",
        "chars": "Race ",
        "format": "text/plain"
      }
    },
    {
      "@id": "https://elucidate.dlcs-ida.org/anno/faa476750615e2ef2331452711704c5d/12",
      "@type": "oa:Annotation",
      "motivation": "sc:painting",
      "on": "https://presley.dlcs-ida.org/iiif/idatest01/_roll_M-1070_01_cvs-131-367/canvas/c252#xywh=1324,1027,514,56",
      "resource": {
        "@type": "cnt:ContentAsText",
        "chars": "Slaoue, ae ",
        "format": "text/plain"
      }
    },
    {
      "@id": "https://elucidate.dlcs-ida.org/anno/faa476750615e2ef2331452711704c5d/13",
      "@type": "oa:Annotation",
      "motivation": "sc:painting",
      "on": "https://presley.dlcs-ida.org/iiif/idatest01/_roll_M-1070_01_cvs-131-367/canvas/c252#xywh=564,1109,284,40",
      "resource": {
        "@type": "cnt:ContentAsText",
        "chars": "sut Oee ",
        "format": "text/plain"
      }
    },
    {
      "@id": "https://elucidate.dlcs-ida.org/anno/faa476750615e2ef2331452711704c5d/14",
      "@type": "oa:Annotation",
      "motivation": "sc:painting",
      "on": "https://presley.dlcs-ida.org/iiif/idatest01/_roll_M-1070_01_cvs-131-367/canvas/c252#xywh=971,1117,132,34",
      "resource": {
        "@type": "cnt:ContentAsText",
        "chars": "a thor ",
        "format": "text/plain"
      }
    },
    {
      "@id": "https://elucidate.dlcs-ida.org/anno/faa476750615e2ef2331452711704c5d/15",
      "@type": "oa:Annotation",
      "motivation": "sc:painting",
      "on": "https://presley.dlcs-ida.org/iiif/idatest01/_roll_M-1070_01_cvs-131-367/canvas/c252#xywh=690,1194,279,39",
      "resource": {
        "@type": "cnt:ContentAsText",
        "chars": "ead Old ",
        "format": "text/plain"
      }
    },
    {
      "@id": "https://elucidate.dlcs-ida.org/anno/faa476750615e2ef2331452711704c5d/16",
      "@type": "oa:Annotation",
      "motivation": "sc:painting",
      "on": "https://presley.dlcs-ida.org/iiif/idatest01/_roll_M-1070_01_cvs-131-367/canvas/c252#xywh=818,1375,236,25",
      "resource": {
        "@type": "cnt:ContentAsText",
        "chars": "came ",
        "format": "text/plain"
      }
    },
    {
      "@id": "https://elucidate.dlcs-ida.org/anno/faa476750615e2ef2331452711704c5d/17",
      "@type": "oa:Annotation",
      "motivation": "sc:painting",
      "on": "https://presley.dlcs-ida.org/iiif/idatest01/_roll_M-1070_01_cvs-131-367/canvas/c252#xywh=1298,1186,555,61",
      "resource": {
        "@type": "cnt:ContentAsText",
        "chars": ", Nestezees, 2SA ",
        "format": "text/plain"
      }
    },
    {
      "@id": "https://elucidate.dlcs-ida.org/anno/faa476750615e2ef2331452711704c5d/18",
      "@type": "oa:Annotation",
      "motivation": "sc:painting",
      "on": "https://presley.dlcs-ida.org/iiif/idatest01/_roll_M-1070_01_cvs-131-367/canvas/c252#xywh=495,1250,848,95",
      "resource": {
        "@type": "cnt:ContentAsText",
        "chars": "aru Cote for why Mlangenges ",
        "format": "text/plain"
      }
    },
    {
      "@id": "https://elucidate.dlcs-ida.org/anno/faa476750615e2ef2331452711704c5d/19",
      "@type": "oa:Annotation",
      "motivation": "sc:painting",
      "on": "https://presley.dlcs-ida.org/iiif/idatest01/_roll_M-1070_01_cvs-131-367/canvas/c252#xywh=1344,1261,33,84",
      "resource": {
        "@type": "cnt:ContentAsText",
        "chars": ". ",
        "format": "text/plain"
      }
    },
    {
      "@id": "https://elucidate.dlcs-ida.org/anno/faa476750615e2ef2331452711704c5d/20",
      "@type": "oa:Annotation",
      "motivation": "sc:painting",
      "on": "https://presley.dlcs-ida.org/iiif/idatest01/_roll_M-1070_01_cvs-131-367/canvas/c252#xywh=1419,1269,438,62",
      "resource": {
        "@type": "cnt:ContentAsText",
        "chars": "ota Selke A M ",
        "format": "text/plain"
      }
    },
    {
      "@id": "https://elucidate.dlcs-ida.org/anno/faa476750615e2ef2331452711704c5d/21",
      "@type": "oa:Annotation",
      "motivation": "sc:painting",
      "on": "https://presley.dlcs-ida.org/iiif/idatest01/_roll_M-1070_01_cvs-131-367/canvas/c252#xywh=1156,1348,97,63",
      "resource": {
        "@type": "cnt:ContentAsText",
        "chars": "breu ",
        "format": "text/plain"
      }
    },
    {
      "@id": "https://elucidate.dlcs-ida.org/anno/faa476750615e2ef2331452711704c5d/22",
      "@type": "oa:Annotation",
      "motivation": "sc:painting",
      "on": "https://presley.dlcs-ida.org/iiif/idatest01/_roll_M-1070_01_cvs-131-367/canvas/c252#xywh=1314,1355,322,64",
      "resource": {
        "@type": "cnt:ContentAsText",
        "chars": "see blan ",
        "format": "text/plain"
      }
    },
    {
      "@id": "https://elucidate.dlcs-ida.org/anno/faa476750615e2ef2331452711704c5d/23",
      "@type": "oa:Annotation",
      "motivation": "sc:painting",
      "on": "https://presley.dlcs-ida.org/iiif/idatest01/_roll_M-1070_01_cvs-131-367/canvas/c252#xywh=501,1422,749,72",
      "resource": {
        "@type": "cnt:ContentAsText",
        "chars": "lice opter 18 Se ",
        "format": "text/plain"
      }
    },
    {
      "@id": "https://elucidate.dlcs-ida.org/anno/faa476750615e2ef2331452711704c5d/24",
      "@type": "oa:Annotation",
      "motivation": "sc:painting",
      "on": "https://presley.dlcs-ida.org/iiif/idatest01/_roll_M-1070_01_cvs-131-367/canvas/c252#xywh=504,1507,1262,81",
      "resource": {
        "@type": "cnt:ContentAsText",
        "chars": "A his receivine at your losses are. ",
        "format": "text/plain"
      }
    },
    {
      "@id": "https://elucidate.dlcs-ida.org/anno/faa476750615e2ef2331452711704c5d/25",
      "@type": "oa:Annotation",
      "motivation": "sc:painting",
      "on": "https://presley.dlcs-ida.org/iiif/idatest01/_roll_M-1070_01_cvs-131-367/canvas/c252#xywh=483,1592,106,56",
      "resource": {
        "@type": "cnt:ContentAsText",
        "chars": "medz ",
        "format": "text/plain"
      }
    },
    {
      "@id": "https://elucidate.dlcs-ida.org/anno/faa476750615e2ef2331452711704c5d/26",
      "@type": "oa:Annotation",
      "motivation": "sc:painting",
      "on": "https://presley.dlcs-ida.org/iiif/idatest01/_roll_M-1070_01_cvs-131-367/canvas/c252#xywh=643,1592,408,55",
      "resource": {
        "@type": "cnt:ContentAsText",
        "chars": "the accounts ",
        "format": "text/plain"
      }
    },
    {
      "@id": "https://elucidate.dlcs-ida.org/anno/faa476750615e2ef2331452711704c5d/27",
      "@type": "oa:Annotation",
      "motivation": "sc:painting",
      "on": "https://presley.dlcs-ida.org/iiif/idatest01/_roll_M-1070_01_cvs-131-367/canvas/c252#xywh=1082,1595,239,53",
      "resource": {
        "@type": "cnt:ContentAsText",
        "chars": "of Asive ",
        "format": "text/plain"
      }
    },
    {
      "@id": "https://elucidate.dlcs-ida.org/anno/faa476750615e2ef2331452711704c5d/28",
      "@type": "oa:Annotation",
      "motivation": "sc:painting",
      "on": "https://presley.dlcs-ida.org/iiif/idatest01/_roll_M-1070_01_cvs-131-367/canvas/c252#xywh=1377,1611,450,43",
      "resource": {
        "@type": "cnt:ContentAsText",
        "chars": "their lence, eelie ",
        "format": "text/plain"
      }
    },
    {
      "@id": "https://elucidate.dlcs-ida.org/anno/faa476750615e2ef2331452711704c5d/29",
      "@type": "oa:Annotation",
      "motivation": "sc:painting",
      "on": "https://presley.dlcs-ida.org/iiif/idatest01/_roll_M-1070_01_cvs-131-367/canvas/c252#xywh=503,1679,411,61",
      "resource": {
        "@type": "cnt:ContentAsText",
        "chars": "or by fely ",
        "format": "text/plain"
      }
    },
    {
      "@id": "https://elucidate.dlcs-ida.org/anno/faa476750615e2ef2331452711704c5d/30",
      "@type": "oa:Annotation",
      "motivation": "sc:painting",
      "on": "https://presley.dlcs-ida.org/iiif/idatest01/_roll_M-1070_01_cvs-131-367/canvas/c252#xywh=963,1687,897,92",
      "resource": {
        "@type": "cnt:ContentAsText",
        "chars": "the units are ok an outset ",
        "format": "text/plain"
      }
    },
    {
      "@id": "https://elucidate.dlcs-ida.org/anno/faa476750615e2ef2331452711704c5d/31",
      "@type": "oa:Annotation",
      "motivation": "sc:painting",
      "on": "https://presley.dlcs-ida.org/iiif/idatest01/_roll_M-1070_01_cvs-131-367/canvas/c252#xywh=491,1764,1332,57",
      "resource": {
        "@type": "cnt:ContentAsText",
        "chars": "led teles Aleni aеitiacy on Raeda 1 has Peo ",
        "format": "text/plain"
      }
    },
    {
      "@id": "https://elucidate.dlcs-ida.org/anno/faa476750615e2ef2331452711704c5d/32",
      "@type": "oa:Annotation",
      "motivation": "sc:painting",
      "on": "https://presley.dlcs-ida.org/iiif/idatest01/_roll_M-1070_01_cvs-131-367/canvas/c252#xywh=444,1846,315,75",
      "resource": {
        "@type": "cnt:ContentAsText",
        "chars": "eMach ",
        "format": "text/plain"
      }
    },
    {
      "@id": "https://elucidate.dlcs-ida.org/anno/faa476750615e2ef2331452711704c5d/33",
      "@type": "oa:Annotation",
      "motivation": "sc:painting",
      "on": "https://presley.dlcs-ida.org/iiif/idatest01/_roll_M-1070_01_cvs-131-367/canvas/c252#xywh=676,1836,269,75",
      "resource": {
        "@type": "cnt:ContentAsText",
        "chars": "ch1899 ",
        "format": "text/plain"
      }
    },
    {
      "@id": "https://elucidate.dlcs-ida.org/anno/faa476750615e2ef2331452711704c5d/34",
      "@type": "oa:Annotation",
      "motivation": "sc:painting",
      "on": "https://presley.dlcs-ida.org/iiif/idatest01/_roll_M-1070_01_cvs-131-367/canvas/c252#xywh=939,1843,288,80",
      "resource": {
        "@type": "cnt:ContentAsText",
        "chars": ". it hire ",
        "format": "text/plain"
      }
    },
    {
      "@id": "https://elucidate.dlcs-ida.org/anno/faa476750615e2ef2331452711704c5d/35",
      "@type": "oa:Annotation",
      "motivation": "sc:painting",
      "on": "https://presley.dlcs-ida.org/iiif/idatest01/_roll_M-1070_01_cvs-131-367/canvas/c252#xywh=1272,1868,377,52",
      "resource": {
        "@type": "cnt:ContentAsText",
        "chars": "acy assert ",
        "format": "text/plain"
      }
    },
    {
      "@id": "https://elucidate.dlcs-ida.org/anno/faa476750615e2ef2331452711704c5d/36",
      "@type": "oa:Annotation",
      "motivation": "sc:painting",
      "on": "https://presley.dlcs-ida.org/iiif/idatest01/_roll_M-1070_01_cvs-131-367/canvas/c252#xywh=1647,1873,158,52",
      "resource": {
        "@type": "cnt:ContentAsText",
        "chars": "army ",
        "format": "text/plain"
      }
    },
    {
      "@id": "https://elucidate.dlcs-ida.org/anno/faa476750615e2ef2331452711704c5d/37",
      "@type": "oa:Annotation",
      "motivation": "sc:painting",
      "on": "https://presley.dlcs-ida.org/iiif/idatest01/_roll_M-1070_01_cvs-131-367/canvas/c252#xywh=337,1915,371,74",
      "resource": {
        "@type": "cnt:ContentAsText",
        "chars": "A| Ms her ",
        "format": "text/plain"
      }
    },
    {
      "@id": "https://elucidate.dlcs-ida.org/anno/faa476750615e2ef2331452711704c5d/38",
      "@type": "oa:Annotation",
      "motivation": "sc:painting",
      "on": "https://presley.dlcs-ida.org/iiif/idatest01/_roll_M-1070_01_cvs-131-367/canvas/c252#xywh=303,2002,334,98",
      "resource": {
        "@type": "cnt:ContentAsText",
        "chars": "- Alice ",
        "format": "text/plain"
      }
    },
    {
      "@id": "https://elucidate.dlcs-ida.org/anno/faa476750615e2ef2331452711704c5d/39",
      "@type": "oa:Annotation",
      "motivation": "sc:painting",
      "on": "https://presley.dlcs-ida.org/iiif/idatest01/_roll_M-1070_01_cvs-131-367/canvas/c252#xywh=810,2008,1081,74",
      "resource": {
        "@type": "cnt:ContentAsText",
        "chars": "face the accusaceutal Lties' sons ",
        "format": "text/plain"
      }
    },
    {
      "@id": "https://elucidate.dlcs-ida.org/anno/faa476750615e2ef2331452711704c5d/40",
      "@type": "oa:Annotation",
      "motivation": "sc:painting",
      "on": "https://presley.dlcs-ida.org/iiif/idatest01/_roll_M-1070_01_cvs-131-367/canvas/c252#xywh=523,2088,358,88",
      "resource": {
        "@type": "cnt:ContentAsText",
        "chars": "The feeding ",
        "format": "text/plain"
      }
    },
    {
      "@id": "https://elucidate.dlcs-ida.org/anno/faa476750615e2ef2331452711704c5d/41",
      "@type": "oa:Annotation",
      "motivation": "sc:painting",
      "on": "https://presley.dlcs-ida.org/iiif/idatest01/_roll_M-1070_01_cvs-131-367/canvas/c252#xywh=961,2106,464,50",
      "resource": {
        "@type": "cnt:ContentAsText",
        "chars": "tice. ars shers ",
        "format": "text/plain"
      }
    },
    {
      "@id": "https://elucidate.dlcs-ida.org/anno/faa476750615e2ef2331452711704c5d/42",
      "@type": "oa:Annotation",
      "motivation": "sc:painting",
      "on": "https://presley.dlcs-ida.org/iiif/idatest01/_roll_M-1070_01_cvs-131-367/canvas/c252#xywh=1461,2107,270,53",
      "resource": {
        "@type": "cnt:ContentAsText",
        "chars": "as heeeeee. ",
        "format": "text/plain"
      }
    },
    {
      "@id": "https://elucidate.dlcs-ida.org/anno/faa476750615e2ef2331452711704c5d/43",
      "@type": "oa:Annotation",
      "motivation": "sc:painting",
      "on": "https://presley.dlcs-ida.org/iiif/idatest01/_roll_M-1070_01_cvs-131-367/canvas/c252#xywh=489,2186,437,46",
      "resource": {
        "@type": "cnt:ContentAsText",
        "chars": "oletal di to k ",
        "format": "text/plain"
      }
    },
    {
      "@id": "https://elucidate.dlcs-ida.org/anno/faa476750615e2ef2331452711704c5d/44",
      "@type": "oa:Annotation",
      "motivation": "sc:painting",
      "on": "https://presley.dlcs-ida.org/iiif/idatest01/_roll_M-1070_01_cvs-131-367/canvas/c252#xywh=459,2252,536,81",
      "resource": {
        "@type": "cnt:ContentAsText",
        "chars": "efs les ordes ",
        "format": "text/plain"
      }
    },
    {
      "@id": "https://elucidate.dlcs-ida.org/anno/faa476750615e2ef2331452711704c5d/45",
      "@type": "oa:Annotation",
      "motivation": "sc:painting",
      "on": "https://presley.dlcs-ida.org/iiif/idatest01/_roll_M-1070_01_cvs-131-367/canvas/c252#xywh=1582,2286,322,61",
      "resource": {
        "@type": "cnt:ContentAsText",
        "chars": "/, forms. ",
        "format": "text/plain"
      }
    },
    {
      "@id": "https://elucidate.dlcs-ida.org/anno/faa476750615e2ef2331452711704c5d/46",
      "@type": "oa:Annotation",
      "motivation": "sc:painting",
      "on": "https://presley.dlcs-ida.org/iiif/idatest01/_roll_M-1070_01_cvs-131-367/canvas/c252#xywh=526,2342,235,52",
      "resource": {
        "@type": "cnt:ContentAsText",
        "chars": "Gaeozy ",
        "format": "text/plain"
      }
    },
    {
      "@id": "https://elucidate.dlcs-ida.org/anno/faa476750615e2ef2331452711704c5d/47",
      "@type": "oa:Annotation",
      "motivation": "sc:painting",
      "on": "https://presley.dlcs-ida.org/iiif/idatest01/_roll_M-1070_01_cvs-131-367/canvas/c252#xywh=1556,2371,314,50",
      "resource": {
        "@type": "cnt:ContentAsText",
        "chars": "A 7 sensus ",
        "format": "text/plain"
      }
    },
    {
      "@id": "https://elucidate.dlcs-ida.org/anno/faa476750615e2ef2331452711704c5d/48",
      "@type": "oa:Annotation",
      "motivation": "sc:painting",
      "on": "https://presley.dlcs-ida.org/iiif/idatest01/_roll_M-1070_01_cvs-131-367/canvas/c252#xywh=489,2424,180,51",
      "resource": {
        "@type": "cnt:ContentAsText",
        "chars": "Seaеew ",
        "format": "text/plain"
      }
    },
    {
      "@id": "https://elucidate.dlcs-ida.org/anno/faa476750615e2ef2331452711704c5d/49",
      "@type": "oa:Annotation",
      "motivation": "sc:painting",
      "on": "https://presley.dlcs-ida.org/iiif/idatest01/_roll_M-1070_01_cvs-131-367/canvas/c252#xywh=1587,2438,161,68",
      "resource": {
        "@type": "cnt:ContentAsText",
        "chars": "So 8. ",
        "format": "text/plain"
      }
    },
    {
      "@id": "https://elucidate.dlcs-ida.org/anno/faa476750615e2ef2331452711704c5d/50",
      "@type": "oa:Annotation",
      "motivation": "sc:painting",
      "on": "https://presley.dlcs-ida.org/iiif/idatest01/_roll_M-1070_01_cvs-131-367/canvas/c252#xywh=518,2502,159,84",
      "resource": {
        "@type": "cnt:ContentAsText",
        "chars": "Oo fee ",
        "format": "text/plain"
      }
    },
    {
      "@id": "https://elucidate.dlcs-ida.org/anno/faa476750615e2ef2331452711704c5d/51",
      "@type": "oa:Annotation",
      "motivation": "sc:painting",
      "on": "https://presley.dlcs-ida.org/iiif/idatest01/_roll_M-1070_01_cvs-131-367/canvas/c252#xywh=1587,2522,269,60",
      "resource": {
        "@type": "cnt:ContentAsText",
        "chars": "so votes ",
        "format": "text/plain"
      }
    },
    {
      "@id": "https://elucidate.dlcs-ida.org/anno/faa476750615e2ef2331452711704c5d/52",
      "@type": "oa:Annotation",
      "motivation": "sc:painting",
      "on": "https://presley.dlcs-ida.org/iiif/idatest01/_roll_M-1070_01_cvs-131-367/canvas/c252#xywh=486,2597,292,50",
      "resource": {
        "@type": "cnt:ContentAsText",
        "chars": "Gorew hiae ",
        "format": "text/plain"
      }
    },
    {
      "@id": "https://elucidate.dlcs-ida.org/anno/faa476750615e2ef2331452711704c5d/53",
      "@type": "oa:Annotation",
      "motivation": "sc:painting",
      "on": "https://presley.dlcs-ida.org/iiif/idatest01/_roll_M-1070_01_cvs-131-367/canvas/c252#xywh=1518,2612,83,42",
      "resource": {
        "@type": "cnt:ContentAsText",
        "chars": "3/ 4 ",
        "format": "text/plain"
      }
    },
    {
      "@id": "https://elucidate.dlcs-ida.org/anno/faa476750615e2ef2331452711704c5d/54",
      "@type": "oa:Annotation",
      "motivation": "sc:painting",
      "on": "https://presley.dlcs-ida.org/iiif/idatest01/_roll_M-1070_01_cvs-131-367/canvas/c252#xywh=1630,2618,132,41",
      "resource": {
        "@type": "cnt:ContentAsText",
        "chars": "4 bn ",
        "format": "text/plain"
      }
    },
    {
      "@id": "https://elucidate.dlcs-ida.org/anno/faa476750615e2ef2331452711704c5d/55",
      "@type": "oa:Annotation",
      "motivation": "sc:painting",
      "on": "https://presley.dlcs-ida.org/iiif/idatest01/_roll_M-1070_01_cvs-131-367/canvas/c252#xywh=1804,2634,40,24",
      "resource": {
        "@type": "cnt:ContentAsText",
        "chars": "als ",
        "format": "text/plain"
      }
    },
    {
      "@id": "https://elucidate.dlcs-ida.org/anno/faa476750615e2ef2331452711704c5d/56",
      "@type": "oa:Annotation",
      "motivation": "sc:painting",
      "on": "https://presley.dlcs-ida.org/iiif/idatest01/_roll_M-1070_01_cvs-131-367/canvas/c252#xywh=1181,2682,459,71",
      "resource": {
        "@type": "cnt:ContentAsText",
        "chars": "( 22- 3Past ",
        "format": "text/plain"
      }
    },
    {
      "@id": "https://elucidate.dlcs-ida.org/anno/faa476750615e2ef2331452711704c5d/57",
      "@type": "oa:Annotation",
      "motivation": "sc:painting",
      "on": "https://presley.dlcs-ida.org/iiif/idatest01/_roll_M-1070_01_cvs-131-367/canvas/c252#xywh=1684,2690,170,75",
      "resource": {
        "@type": "cnt:ContentAsText",
        "chars": "permits ",
        "format": "text/plain"
      }
    },
    {
      "@id": "https://elucidate.dlcs-ida.org/anno/faa476750615e2ef2331452711704c5d/58",
      "@type": "oa:Annotation",
      "motivation": "sc:painting",
      "on": "https://presley.dlcs-ida.org/iiif/idatest01/_roll_M-1070_01_cvs-131-367/canvas/c252#xywh=1337,2146,59,45",
      "resource": {
        "@type": "cnt:ContentAsText",
        "chars": "deer ",
        "format": "text/plain"
      }
    },
    {
      "@id": "https://elucidate.dlcs-ida.org/anno/faa476750615e2ef2331452711704c5d/59",
      "@type": "oa:Annotation",
      "motivation": "sc:painting",
      "on": "https://presley.dlcs-ida.org/iiif/idatest01/_roll_M-1070_01_cvs-131-367/canvas/c252#xywh=1779,2467,91,39",
      "resource": {
        "@type": "cnt:ContentAsText",
        "chars": "end ",
        "format": "text/plain"
      }
    }
  ]
}