{
  "@context": "http://iiif.io/api/presentation/2/context.json",
  "@type": "sc:AnnotationList",
  "@id": "https://digirati-co-uk.github.io/ida-exported-data/iiif/annotations/_roll_santa-fe-indian-school-yearbooks_1984-1985_cvs-1-168/d3217dae07333a4aa0f1a9e7e3b3885b/annotations.json",
  "resources": [
    {
      "motivation": "oa:tagging",
      "on": "https://presley.dlcs-ida.org/iiif/idatest01/_roll_santa-fe-indian-school-yearbooks_1984-1985_cvs-1-168/canvas/c36",
      "@id": "https://elucidate.dlcs-ida.org/annotation/w3c/d3217dae07333a4aa0f1a9e7e3b3885b/9240bb17-de03-46f8-b891-3855595dac00",
      "@type": "oa:Annotation",
      "resource": [
        {
          "@type": "oa:Tag",
          "chars": "entity:Series"
        },
        {
          "chars": "<a href=\"https://omeka.dlcs-ida.org/s/ida/page/topics/series/santa-fe-indian-school-yearbooks\">https://omeka.dlcs-ida.org/s/ida/page/topics/series/santa-fe-indian-school-yearbooks</a>",
          "format": "application/html"
        },
        {
          "@type": "oa:Tag",
          "chars": "santa-fe-indian-school-yearbooks"
        }
      ]
    },
    {
      "motivation": "oa:tagging",
      "on": "https://presley.dlcs-ida.org/iiif/idatest01/_roll_santa-fe-indian-school-yearbooks_1984-1985_cvs-1-168/canvas/c36",
      "@id": "https://elucidate.dlcs-ida.org/annotation/w3c/d3217dae07333a4aa0f1a9e7e3b3885b/a083eb65-5212-4a18-9e4a-75d1d9b8e2b0",
      "@type": "oa:Annotation",
      "resource": [
        {
          "@type": "oa:Tag",
          "chars": "entity:Roll"
        },
        {
          "chars": "<a href=\"https://omeka.dlcs-ida.org/s/ida/page/topics/roll/santa-fe-indian-school-yearbooks_1984-1985\">https://omeka.dlcs-ida.org/s/ida/page/topics/roll/santa-fe-indian-school-yearbooks_1984-1985</a>",
          "format": "application/html"
        },
        {
          "@type": "oa:Tag",
          "chars": "santa-fe-indian-school-yearbooks_1984-1985"
        }
      ]
    },
    {
      "motivation": "oa:tagging",
      "on": "https://presley.dlcs-ida.org/iiif/idatest01/_roll_santa-fe-indian-school-yearbooks_1984-1985_cvs-1-168/canvas/c36#xywh=459,1321,281,32",
      "@id": "https://elucidate.dlcs-ida.org/annotation/w3c/d3217dae07333a4aa0f1a9e7e3b3885b/9956a4a3-6928-47d4-89e0-57b3a5df234d",
      "@type": "oa:Annotation",
      "resource": [
        {
          "chars": "<a href=\"https://omeka.dlcs-ida.org/s/ida/page/topics/virtual:person/alvanessa+nutumya\">https://omeka.dlcs-ida.org/s/ida/page/topics/virtual:person/alvanessa+nutumya</a>",
          "format": "application/html"
        },
        {
          "@type": "oa:Tag",
          "chars": "entity:person"
        },
        {
          "@type": "oa:Tag",
          "chars": "Alvanessa Nutumya"
        }
      ]
    },
    {
      "motivation": "oa:tagging",
      "on": "https://presley.dlcs-ida.org/iiif/idatest01/_roll_santa-fe-indian-school-yearbooks_1984-1985_cvs-1-168/canvas/c36#xywh=506,944,242,37",
      "@id": "https://elucidate.dlcs-ida.org/annotation/w3c/d3217dae07333a4aa0f1a9e7e3b3885b/a92a0ac3-4976-4be4-b541-8d3a529d5650",
      "@type": "oa:Annotation",
      "resource": [
        {
          "@type": "oa:Tag",
          "chars": "entity:person"
        },
        {
          "@type": "oa:Tag",
          "chars": "Mike Murphy Jon Naranjo Adrianne Norris"
        },
        {
          "chars": "<a href=\"https://omeka.dlcs-ida.org/s/ida/page/topics/virtual:person/mike+murphy+jon+naranjo+adrianne+norris\">https://omeka.dlcs-ida.org/s/ida/page/topics/virtual:person/mike+murphy+jon+naranjo+adrianne+norris</a>",
          "format": "application/html"
        }
      ]
    },
    {
      "motivation": "oa:tagging",
      "on": "https://presley.dlcs-ida.org/iiif/idatest01/_roll_santa-fe-indian-school-yearbooks_1984-1985_cvs-1-168/canvas/c36#xywh=167,3259,34,18",
      "@id": "https://elucidate.dlcs-ida.org/annotation/w3c/d3217dae07333a4aa0f1a9e7e3b3885b/0fad0bea-7598-47ab-99f3-600ee3262341",
      "@type": "oa:Annotation",
      "resource": [
        {
          "@type": "oa:Tag",
          "chars": "entity:date"
        },
        {
          "@type": "oa:Tag",
          "chars": "32"
        },
        {
          "chars": "<a href=\"https://omeka.dlcs-ida.org/s/ida/page/topics/virtual:date/32\">https://omeka.dlcs-ida.org/s/ida/page/topics/virtual:date/32</a>",
          "format": "application/html"
        }
      ]
    },
    {
      "motivation": "oa:tagging",
      "on": "https://presley.dlcs-ida.org/iiif/idatest01/_roll_santa-fe-indian-school-yearbooks_1984-1985_cvs-1-168/canvas/c36#xywh=611,870,136,39",
      "@id": "https://elucidate.dlcs-ida.org/annotation/w3c/d3217dae07333a4aa0f1a9e7e3b3885b/3d6e67c4-537a-4c5a-b210-c5ab578db496",
      "@type": "oa:Annotation",
      "resource": [
        {
          "chars": "<a href=\"https://omeka.dlcs-ida.org/s/ida/page/topics/virtual:gpe/martinez\">https://omeka.dlcs-ida.org/s/ida/page/topics/virtual:gpe/martinez</a>",
          "format": "application/html"
        },
        {
          "@type": "oa:Tag",
          "chars": "Martinez"
        },
        {
          "@type": "oa:Tag",
          "chars": "entity:gpe"
        }
      ]
    },
    {
      "motivation": "oa:tagging",
      "on": "https://presley.dlcs-ida.org/iiif/idatest01/_roll_santa-fe-indian-school-yearbooks_1984-1985_cvs-1-168/canvas/c36#xywh=504,1733,234,37",
      "@id": "https://elucidate.dlcs-ida.org/annotation/w3c/d3217dae07333a4aa0f1a9e7e3b3885b/d8882c1f-3ff2-4778-b81c-352c32f0352b",
      "@type": "oa:Annotation",
      "resource": [
        {
          "@type": "oa:Tag",
          "chars": "entity:person"
        },
        {
          "@type": "oa:Tag",
          "chars": "Carl Peno Clarina"
        },
        {
          "chars": "<a href=\"https://omeka.dlcs-ida.org/s/ida/page/topics/virtual:person/carl+peno+clarina\">https://omeka.dlcs-ida.org/s/ida/page/topics/virtual:person/carl+peno+clarina</a>",
          "format": "application/html"
        }
      ]
    },
    {
      "motivation": "oa:tagging",
      "on": "https://presley.dlcs-ida.org/iiif/idatest01/_roll_santa-fe-indian-school-yearbooks_1984-1985_cvs-1-168/canvas/c36#xywh=530,1358,212,37",
      "@id": "https://elucidate.dlcs-ida.org/annotation/w3c/d3217dae07333a4aa0f1a9e7e3b3885b/2a0f2b21-9171-44de-87e8-608e645d0162",
      "@type": "oa:Annotation",
      "resource": [
        {
          "@type": "oa:Tag",
          "chars": "entity:person"
        },
        {
          "@type": "oa:Tag",
          "chars": "Keith Pacheco"
        },
        {
          "chars": "<a href=\"https://omeka.dlcs-ida.org/s/ida/page/topics/virtual:person/keith+pacheco\">https://omeka.dlcs-ida.org/s/ida/page/topics/virtual:person/keith+pacheco</a>",
          "format": "application/html"
        }
      ]
    },
    {
      "motivation": "oa:tagging",
      "on": "https://presley.dlcs-ida.org/iiif/idatest01/_roll_santa-fe-indian-school-yearbooks_1984-1985_cvs-1-168/canvas/c36#xywh=578,1435,161,35",
      "@id": "https://elucidate.dlcs-ida.org/annotation/w3c/d3217dae07333a4aa0f1a9e7e3b3885b/a1a65765-f988-4763-ac57-ca74fd1bef8b",
      "@type": "oa:Annotation",
      "resource": [
        {
          "@type": "oa:Tag",
          "chars": "Carol Piaso"
        },
        {
          "chars": "<a href=\"https://omeka.dlcs-ida.org/s/ida/page/topics/virtual:person/carol+piaso\">https://omeka.dlcs-ida.org/s/ida/page/topics/virtual:person/carol+piaso</a>",
          "format": "application/html"
        },
        {
          "@type": "oa:Tag",
          "chars": "entity:person"
        }
      ]
    },
    {
      "motivation": "oa:tagging",
      "on": "https://presley.dlcs-ida.org/iiif/idatest01/_roll_santa-fe-indian-school-yearbooks_1984-1985_cvs-1-168/canvas/c36#xywh=523,906,224,38",
      "@id": "https://elucidate.dlcs-ida.org/annotation/w3c/d3217dae07333a4aa0f1a9e7e3b3885b/1345eb4e-24dc-4259-af4c-98ab15c8b799",
      "@type": "oa:Annotation",
      "resource": [
        {
          "@type": "oa:Tag",
          "chars": "entity:person"
        },
        {
          "chars": "<a href=\"https://omeka.dlcs-ida.org/s/ida/page/topics/virtual:person/bruce+montoya\">https://omeka.dlcs-ida.org/s/ida/page/topics/virtual:person/bruce+montoya</a>",
          "format": "application/html"
        },
        {
          "@type": "oa:Tag",
          "chars": "Bruce Montoya"
        }
      ]
    },
    {
      "motivation": "oa:tagging",
      "on": "https://presley.dlcs-ida.org/iiif/idatest01/_roll_santa-fe-indian-school-yearbooks_1984-1985_cvs-1-168/canvas/c36#xywh=518,386,232,108",
      "@id": "https://elucidate.dlcs-ida.org/annotation/w3c/d3217dae07333a4aa0f1a9e7e3b3885b/6109b203-4218-4efe-aac3-570a1294deab",
      "@type": "oa:Annotation",
      "resource": [
        {
          "@type": "oa:Tag",
          "chars": "entity:person"
        },
        {
          "@type": "oa:Tag",
          "chars": "Jamie Laban Reanna Lasiloo Sandra Lauriano"
        },
        {
          "chars": "<a href=\"https://omeka.dlcs-ida.org/s/ida/page/topics/virtual:person/jamie+laban+reanna+lasiloo+sandra+lauriano\">https://omeka.dlcs-ida.org/s/ida/page/topics/virtual:person/jamie+laban+reanna+lasiloo+sandra+lauriano</a>",
          "format": "application/html"
        }
      ]
    },
    {
      "motivation": "oa:tagging",
      "on": "https://presley.dlcs-ida.org/iiif/idatest01/_roll_santa-fe-indian-school-yearbooks_1984-1985_cvs-1-168/canvas/c36#xywh=425,2182,310,37",
      "@id": "https://elucidate.dlcs-ida.org/annotation/w3c/d3217dae07333a4aa0f1a9e7e3b3885b/ed56036b-172d-4462-b63c-99c7565ea923",
      "@type": "oa:Annotation",
      "resource": [
        {
          "@type": "oa:Tag",
          "chars": "entity:org"
        },
        {
          "chars": "<a href=\"https://omeka.dlcs-ida.org/s/ida/page/topics/virtual:org/sheryl+poleahla+barbara+polingyonma\">https://omeka.dlcs-ida.org/s/ida/page/topics/virtual:org/sheryl+poleahla+barbara+polingyonma</a>",
          "format": "application/html"
        },
        {
          "@type": "oa:Tag",
          "chars": "Sheryl Poleahla Barbara Polingyonma"
        }
      ]
    }
  ]
}