{
  "@context": "http://iiif.io/api/presentation/2/context.json",
  "@id": "https://digirati-co-uk.github.io/ida-exported-data/iiif/annotations/_roll_M-1011_079_cvs-892-967/ocr_c5aa8b37-392a-4324-ab19-8ccdf3fc3b38/annotations.json",
  "@type": "sc:AnnotationList",
  "resources": [
    {
      "@id": "https://elucidate.dlcs-ida.org/anno/a8fcac4c8fade2166792f64062d815b2/0",
      "@type": "oa:Annotation",
      "motivation": "sc:painting",
      "on": "https://presley.dlcs-ida.org/iiif/idatest01/_roll_M-1011_079_cvs-892-967/canvas/c918#xywh=256,165,120,81",
      "resource": {
        "@type": "cnt:ContentAsText",
        "chars": "0. 0. ",
        "format": "text/plain"
      }
    },
    {
      "@id": "https://elucidate.dlcs-ida.org/anno/a8fcac4c8fade2166792f64062d815b2/1",
      "@type": "oa:Annotation",
      "motivation": "sc:painting",
      "on": "https://presley.dlcs-ida.org/iiif/idatest01/_roll_M-1011_079_cvs-892-967/canvas/c918#xywh=1967,153,105,62",
      "resource": {
        "@type": "cnt:ContentAsText",
        "chars": "67773 ",
        "format": "text/plain"
      }
    },
    {
      "@id": "https://elucidate.dlcs-ida.org/anno/a8fcac4c8fade2166792f64062d815b2/2",
      "@type": "oa:Annotation",
      "motivation": "sc:painting",
      "on": "https://presley.dlcs-ida.org/iiif/idatest01/_roll_M-1011_079_cvs-892-967/canvas/c918#xywh=308,307,654,51",
      "resource": {
        "@type": "cnt:ContentAsText",
        "chars": "1933 Anmaal Statistical Report ",
        "format": "text/plain"
      }
    },
    {
      "@id": "https://elucidate.dlcs-ida.org/anno/a8fcac4c8fade2166792f64062d815b2/3",
      "@type": "oa:Annotation",
      "motivation": "sc:painting",
      "on": "https://presley.dlcs-ida.org/iiif/idatest01/_roll_M-1011_079_cvs-892-967/canvas/c918#xywh=1581,287,513,56",
      "resource": {
        "@type": "cnt:ContentAsText",
        "chars": "Office of Indian Affairs ",
        "format": "text/plain"
      }
    },
    {
      "@id": "https://elucidate.dlcs-ida.org/anno/a8fcac4c8fade2166792f64062d815b2/4",
      "@type": "oa:Annotation",
      "motivation": "sc:painting",
      "on": "https://presley.dlcs-ida.org/iiif/idatest01/_roll_M-1011_079_cvs-892-967/canvas/c918#xywh=291,416,708,51",
      "resource": {
        "@type": "cnt:ContentAsText",
        "chars": "Higomery en dit rino et exto e ",
        "format": "text/plain"
      }
    },
    {
      "@id": "https://elucidate.dlcs-ida.org/anno/a8fcac4c8fade2166792f64062d815b2/5",
      "@type": "oa:Annotation",
      "motivation": "sc:painting",
      "on": "https://presley.dlcs-ida.org/iiif/idatest01/_roll_M-1011_079_cvs-892-967/canvas/c918#xywh=962,396,213,49",
      "resource": {
        "@type": "cnt:ContentAsText",
        "chars": "Section, U ",
        "format": "text/plain"
      }
    },
    {
      "@id": "https://elucidate.dlcs-ida.org/anno/a8fcac4c8fade2166792f64062d815b2/6",
      "@type": "oa:Annotation",
      "motivation": "sc:painting",
      "on": "https://presley.dlcs-ida.org/iiif/idatest01/_roll_M-1011_079_cvs-892-967/canvas/c918#xywh=1271,389,193,55",
      "resource": {
        "@type": "cnt:ContentAsText",
        "chars": "opulation ",
        "format": "text/plain"
      }
    },
    {
      "@id": "https://elucidate.dlcs-ida.org/anno/a8fcac4c8fade2166792f64062d815b2/7",
      "@type": "oa:Annotation",
      "motivation": "sc:painting",
      "on": "https://presley.dlcs-ida.org/iiif/idatest01/_roll_M-1011_079_cvs-892-967/canvas/c918#xywh=1320,411,656,54",
      "resource": {
        "@type": "cnt:ContentAsText",
        "chars": "**** disa mot deesde el ",
        "format": "text/plain"
      }
    },
    {
      "@id": "https://elucidate.dlcs-ida.org/anno/a8fcac4c8fade2166792f64062d815b2/8",
      "@type": "oa:Annotation",
      "motivation": "sc:painting",
      "on": "https://presley.dlcs-ida.org/iiif/idatest01/_roll_M-1011_079_cvs-892-967/canvas/c918#xywh=309,480,1191,75",
      "resource": {
        "@type": "cnt:ContentAsText",
        "chars": "State Arizona Reservation Navajo ",
        "format": "text/plain"
      }
    },
    {
      "@id": "https://elucidate.dlcs-ida.org/anno/a8fcac4c8fade2166792f64062d815b2/9",
      "@type": "oa:Annotation",
      "motivation": "sc:painting",
      "on": "https://presley.dlcs-ida.org/iiif/idatest01/_roll_M-1011_079_cvs-892-967/canvas/c918#xywh=1642,500,479,75",
      "resource": {
        "@type": "cnt:ContentAsText",
        "chars": "* Réservation as ",
        "format": "text/plain"
      }
    },
    {
      "@id": "https://elucidate.dlcs-ida.org/anno/a8fcac4c8fade2166792f64062d815b2/10",
      "@type": "oa:Annotation",
      "motivation": "sc:painting",
      "on": "https://presley.dlcs-ida.org/iiif/idatest01/_roll_M-1011_079_cvs-892-967/canvas/c918#xywh=304,571,694,79",
      "resource": {
        "@type": "cnt:ContentAsText",
        "chars": "Agency or Jurisdiction Leupp ",
        "format": "text/plain"
      }
    },
    {
      "@id": "https://elucidate.dlcs-ida.org/anno/a8fcac4c8fade2166792f64062d815b2/11",
      "@type": "oa:Annotation",
      "motivation": "sc:painting",
      "on": "https://presley.dlcs-ida.org/iiif/idatest01/_roll_M-1011_079_cvs-892-967/canvas/c918#xywh=1648,563,343,52",
      "resource": {
        "@type": "cnt:ContentAsText",
        "chars": "Tribe a whole. ",
        "format": "text/plain"
      }
    },
    {
      "@id": "https://elucidate.dlcs-ida.org/anno/a8fcac4c8fade2166792f64062d815b2/12",
      "@type": "oa:Annotation",
      "motivation": "sc:painting",
      "on": "https://presley.dlcs-ida.org/iiif/idatest01/_roll_M-1011_079_cvs-892-967/canvas/c918#xywh=938,648,596,54",
      "resource": {
        "@type": "cnt:ContentAsText",
        "chars": "CENSUS RECAPITULATION SHEET ",
        "format": "text/plain"
      }
    },
    {
      "@id": "https://elucidate.dlcs-ida.org/anno/a8fcac4c8fade2166792f64062d815b2/13",
      "@type": "oa:Annotation",
      "motivation": "sc:painting",
      "on": "https://presley.dlcs-ida.org/iiif/idatest01/_roll_M-1011_079_cvs-892-967/canvas/c918#xywh=940,672,1193,72",
      "resource": {
        "@type": "cnt:ContentAsText",
        "chars": "** Sheet compiled by Hester I, Ashaare ",
        "format": "text/plain"
      }
    },
    {
      "@id": "https://elucidate.dlcs-ida.org/anno/a8fcac4c8fade2166792f64062d815b2/14",
      "@type": "oa:Annotation",
      "motivation": "sc:painting",
      "on": "https://presley.dlcs-ida.org/iiif/idatest01/_roll_M-1011_079_cvs-892-967/canvas/c918#xywh=308,747,673,50",
      "resource": {
        "@type": "cnt:ContentAsText",
        "chars": "Population as of April 1, 1933: ",
        "format": "text/plain"
      }
    },
    {
      "@id": "https://elucidate.dlcs-ida.org/anno/a8fcac4c8fade2166792f64062d815b2/15",
      "@type": "oa:Annotation",
      "motivation": "sc:painting",
      "on": "https://presley.dlcs-ida.org/iiif/idatest01/_roll_M-1011_079_cvs-892-967/canvas/c918#xywh=1209,734,732,51",
      "resource": {
        "@type": "cnt:ContentAsText",
        "chars": "Sheet verified by N, O, B1okal ",
        "format": "text/plain"
      }
    },
    {
      "@id": "https://elucidate.dlcs-ida.org/anno/a8fcac4c8fade2166792f64062d815b2/16",
      "@type": "oa:Annotation",
      "motivation": "sc:painting",
      "on": "https://presley.dlcs-ida.org/iiif/idatest01/_roll_M-1011_079_cvs-892-967/canvas/c918#xywh=313,780,1457,54",
      "resource": {
        "@type": "cnt:ContentAsText",
        "chars": "Before compiling please read instructions on back of this schedule. ",
        "format": "text/plain"
      }
    },
    {
      "@id": "https://elucidate.dlcs-ida.org/anno/a8fcac4c8fade2166792f64062d815b2/17",
      "@type": "oa:Annotation",
      "motivation": "sc:painting",
      "on": "https://presley.dlcs-ida.org/iiif/idatest01/_roll_M-1011_079_cvs-892-967/canvas/c918#xywh=302,843,1801,78",
      "resource": {
        "@type": "cnt:ContentAsText",
        "chars": "1. Total Census April 1, 1932( Must be exactly as the sot Total ir Maled Female ",
        "format": "text/plain"
      }
    },
    {
      "@id": "https://elucidate.dlcs-ida.org/anno/a8fcac4c8fade2166792f64062d815b2/18",
      "@type": "oa:Annotation",
      "motivation": "sc:painting",
      "on": "https://presley.dlcs-ida.org/iiif/idatest01/_roll_M-1011_079_cvs-892-967/canvas/c918#xywh=422,919,914,56",
      "resource": {
        "@type": "cnt:ContentAsText",
        "chars": "reported in Table 2, Commissioner' s Annual ",
        "format": "text/plain"
      }
    },
    {
      "@id": "https://elucidate.dlcs-ida.org/anno/a8fcac4c8fade2166792f64062d815b2/19",
      "@type": "oa:Annotation",
      "motivation": "sc:painting",
      "on": "https://presley.dlcs-ida.org/iiif/idatest01/_roll_M-1011_079_cvs-892-967/canvas/c918#xywh=423,963,869,54",
      "resource": {
        "@type": "cnt:ContentAsText",
        "chars": "Report for total, male, and female)..... ",
        "format": "text/plain"
      }
    },
    {
      "@id": "https://elucidate.dlcs-ida.org/anno/a8fcac4c8fade2166792f64062d815b2/20",
      "@type": "oa:Annotation",
      "motivation": "sc:painting",
      "on": "https://presley.dlcs-ida.org/iiif/idatest01/_roll_M-1011_079_cvs-892-967/canvas/c918#xywh=1450,937,652,71",
      "resource": {
        "@type": "cnt:ContentAsText",
        "chars": ". 1816 907 909. ",
        "format": "text/plain"
      }
    },
    {
      "@id": "https://elucidate.dlcs-ida.org/anno/a8fcac4c8fade2166792f64062d815b2/21",
      "@type": "oa:Annotation",
      "motivation": "sc:painting",
      "on": "https://presley.dlcs-ida.org/iiif/idatest01/_roll_M-1011_079_cvs-892-967/canvas/c918#xywh=310,1032,937,77",
      "resource": {
        "@type": "cnt:ContentAsText",
        "chars": "2. Additions since April 1, 1932, total.... ",
        "format": "text/plain"
      }
    },
    {
      "@id": "https://elucidate.dlcs-ida.org/anno/a8fcac4c8fade2166792f64062d815b2/22",
      "@type": "oa:Annotation",
      "motivation": "sc:painting",
      "on": "https://presley.dlcs-ida.org/iiif/idatest01/_roll_M-1011_079_cvs-892-967/canvas/c918#xywh=354,1083,1070,62",
      "resource": {
        "@type": "cnt:ContentAsText",
        "chars": ". 2- a. Births during the year( April 1, 1932 to ",
        "format": "text/plain"
      }
    },
    {
      "@id": "https://elucidate.dlcs-ida.org/anno/a8fcac4c8fade2166792f64062d815b2/23",
      "@type": "oa:Annotation",
      "motivation": "sc:painting",
      "on": "https://presley.dlcs-ida.org/iiif/idatest01/_roll_M-1011_079_cvs-892-967/canvas/c918#xywh=580,1137,539,60",
      "resource": {
        "@type": "cnt:ContentAsText",
        "chars": "March 31, 1933, only).... ",
        "format": "text/plain"
      }
    },
    {
      "@id": "https://elucidate.dlcs-ida.org/anno/a8fcac4c8fade2166792f64062d815b2/24",
      "@type": "oa:Annotation",
      "motivation": "sc:painting",
      "on": "https://presley.dlcs-ida.org/iiif/idatest01/_roll_M-1011_079_cvs-892-967/canvas/c918#xywh=444,1177,807,64",
      "resource": {
        "@type": "cnt:ContentAsText",
        "chars": "2- b. All other causes................ ",
        "format": "text/plain"
      }
    },
    {
      "@id": "https://elucidate.dlcs-ida.org/anno/a8fcac4c8fade2166792f64062d815b2/25",
      "@type": "oa:Annotation",
      "motivation": "sc:painting",
      "on": "https://presley.dlcs-ida.org/iiif/idatest01/_roll_M-1011_079_cvs-892-967/canvas/c918#xywh=601,1221,894,53",
      "resource": {
        "@type": "cnt:ContentAsText",
        "chars": "2- B( 1). Because of enrollment by Depart-, ",
        "format": "text/plain"
      }
    },
    {
      "@id": "https://elucidate.dlcs-ida.org/anno/a8fcac4c8fade2166792f64062d815b2/26",
      "@type": "oa:Annotation",
      "motivation": "sc:painting",
      "on": "https://presley.dlcs-ida.org/iiif/idatest01/_roll_M-1011_079_cvs-892-967/canvas/c918#xywh=803,1269,469,55",
      "resource": {
        "@type": "cnt:ContentAsText",
        "chars": "mental authority...... ",
        "format": "text/plain"
      }
    },
    {
      "@id": "https://elucidate.dlcs-ida.org/anno/a8fcac4c8fade2166792f64062d815b2/27",
      "@type": "oa:Annotation",
      "motivation": "sc:painting",
      "on": "https://presley.dlcs-ida.org/iiif/idatest01/_roll_M-1011_079_cvs-892-967/canvas/c918#xywh=711,1308,781,51",
      "resource": {
        "@type": "cnt:ContentAsText",
        "chars": "). Because of omission from previous ",
        "format": "text/plain"
      }
    },
    {
      "@id": "https://elucidate.dlcs-ida.org/anno/a8fcac4c8fade2166792f64062d815b2/28",
      "@type": "oa:Annotation",
      "motivation": "sc:painting",
      "on": "https://presley.dlcs-ida.org/iiif/idatest01/_roll_M-1011_079_cvs-892-967/canvas/c918#xywh=388,1372,176,73",
      "resource": {
        "@type": "cnt:ContentAsText",
        "chars": "esa( eje ",
        "format": "text/plain"
      }
    },
    {
      "@id": "https://elucidate.dlcs-ida.org/anno/a8fcac4c8fade2166792f64062d815b2/29",
      "@type": "oa:Annotation",
      "motivation": "sc:painting",
      "on": "https://presley.dlcs-ida.org/iiif/idatest01/_roll_M-1011_079_cvs-892-967/canvas/c918#xywh=795,1362,477,47",
      "resource": {
        "@type": "cnt:ContentAsText",
        "chars": "cen sus rolls.......... ",
        "format": "text/plain"
      }
    },
    {
      "@id": "https://elucidate.dlcs-ida.org/anno/a8fcac4c8fade2166792f64062d815b2/30",
      "@type": "oa:Annotation",
      "motivation": "sc:painting",
      "on": "https://presley.dlcs-ida.org/iiif/idatest01/_roll_M-1011_079_cvs-892-967/canvas/c918#xywh=601,1398,870,50",
      "resource": {
        "@type": "cnt:ContentAsText",
        "chars": "2- 6( 3). Births unreported, but occurring ",
        "format": "text/plain"
      }
    },
    {
      "@id": "https://elucidate.dlcs-ida.org/anno/a8fcac4c8fade2166792f64062d815b2/31",
      "@type": "oa:Annotation",
      "motivation": "sc:painting",
      "on": "https://presley.dlcs-ida.org/iiif/idatest01/_roll_M-1011_079_cvs-892-967/canvas/c918#xywh=795,1440,545,61",
      "resource": {
        "@type": "cnt:ContentAsText",
        "chars": "prior to April 1, 1932... ",
        "format": "text/plain"
      }
    },
    {
      "@id": "https://elucidate.dlcs-ida.org/anno/a8fcac4c8fade2166792f64062d815b2/32",
      "@type": "oa:Annotation",
      "motivation": "sc:painting",
      "on": "https://presley.dlcs-ida.org/iiif/idatest01/_roll_M-1011_079_cvs-892-967/canvas/c918#xywh=605,1493,738,49",
      "resource": {
        "@type": "cnt:ContentAsText",
        "chars": "2- 6( 4). Because of error in sex... ",
        "format": "text/plain"
      }
    },
    {
      "@id": "https://elucidate.dlcs-ida.org/anno/a8fcac4c8fade2166792f64062d815b2/33",
      "@type": "oa:Annotation",
      "motivation": "sc:painting",
      "on": "https://presley.dlcs-ida.org/iiif/idatest01/_roll_M-1011_079_cvs-892-967/canvas/c918#xywh=2032,1036,69,54",
      "resource": {
        "@type": "cnt:ContentAsText",
        "chars": "32. ",
        "format": "text/plain"
      }
    },
    {
      "@id": "https://elucidate.dlcs-ida.org/anno/a8fcac4c8fade2166792f64062d815b2/34",
      "@type": "oa:Annotation",
      "motivation": "sc:painting",
      "on": "https://presley.dlcs-ida.org/iiif/idatest01/_roll_M-1011_079_cvs-892-967/canvas/c918#xywh=2028,1116,111,60",
      "resource": {
        "@type": "cnt:ContentAsText",
        "chars": "288 ",
        "format": "text/plain"
      }
    },
    {
      "@id": "https://elucidate.dlcs-ida.org/anno/a8fcac4c8fade2166792f64062d815b2/35",
      "@type": "oa:Annotation",
      "motivation": "sc:painting",
      "on": "https://presley.dlcs-ida.org/iiif/idatest01/_roll_M-1011_079_cvs-892-967/canvas/c918#xywh=1587,1694,119,43",
      "resource": {
        "@type": "cnt:ContentAsText",
        "chars": "1889 ",
        "format": "text/plain"
      }
    },
    {
      "@id": "https://elucidate.dlcs-ida.org/anno/a8fcac4c8fade2166792f64062d815b2/36",
      "@type": "oa:Annotation",
      "motivation": "sc:painting",
      "on": "https://presley.dlcs-ida.org/iiif/idatest01/_roll_M-1011_079_cvs-892-967/canvas/c918#xywh=1835,1685,251,45",
      "resource": {
        "@type": "cnt:ContentAsText",
        "chars": "948 941 ",
        "format": "text/plain"
      }
    },
    {
      "@id": "https://elucidate.dlcs-ida.org/anno/a8fcac4c8fade2166792f64062d815b2/37",
      "@type": "oa:Annotation",
      "motivation": "sc:painting",
      "on": "https://presley.dlcs-ida.org/iiif/idatest01/_roll_M-1011_079_cvs-892-967/canvas/c918#xywh=1648,1788,42,45",
      "resource": {
        "@type": "cnt:ContentAsText",
        "chars": "34 ",
        "format": "text/plain"
      }
    },
    {
      "@id": "https://elucidate.dlcs-ida.org/anno/a8fcac4c8fade2166792f64062d815b2/38",
      "@type": "oa:Annotation",
      "motivation": "sc:painting",
      "on": "https://presley.dlcs-ida.org/iiif/idatest01/_roll_M-1011_079_cvs-892-967/canvas/c918#xywh=1851,1785,75,46",
      "resource": {
        "@type": "cnt:ContentAsText",
        "chars": "13. ",
        "format": "text/plain"
      }
    },
    {
      "@id": "https://elucidate.dlcs-ida.org/anno/a8fcac4c8fade2166792f64062d815b2/39",
      "@type": "oa:Annotation",
      "motivation": "sc:painting",
      "on": "https://presley.dlcs-ida.org/iiif/idatest01/_roll_M-1011_079_cvs-892-967/canvas/c918#xywh=2032,1785,59,45",
      "resource": {
        "@type": "cnt:ContentAsText",
        "chars": "11 ",
        "format": "text/plain"
      }
    },
    {
      "@id": "https://elucidate.dlcs-ida.org/anno/a8fcac4c8fade2166792f64062d815b2/40",
      "@type": "oa:Annotation",
      "motivation": "sc:painting",
      "on": "https://presley.dlcs-ida.org/iiif/idatest01/_roll_M-1011_079_cvs-892-967/canvas/c918#xywh=1642,1866,53,41",
      "resource": {
        "@type": "cnt:ContentAsText",
        "chars": "18 ",
        "format": "text/plain"
      }
    },
    {
      "@id": "https://elucidate.dlcs-ida.org/anno/a8fcac4c8fade2166792f64062d815b2/41",
      "@type": "oa:Annotation",
      "motivation": "sc:painting",
      "on": "https://presley.dlcs-ida.org/iiif/idatest01/_roll_M-1011_079_cvs-892-967/canvas/c918#xywh=1860,1860,43,46",
      "resource": {
        "@type": "cnt:ContentAsText",
        "chars": "10 ",
        "format": "text/plain"
      }
    },
    {
      "@id": "https://elucidate.dlcs-ida.org/anno/a8fcac4c8fade2166792f64062d815b2/42",
      "@type": "oa:Annotation",
      "motivation": "sc:painting",
      "on": "https://presley.dlcs-ida.org/iiif/idatest01/_roll_M-1011_079_cvs-892-967/canvas/c918#xywh=321,1656,1175,67",
      "resource": {
        "@type": "cnt:ContentAsText",
        "chars": "3. Total Census April 1, 1932, Table 2, Cornissioner' s ",
        "format": "text/plain"
      }
    },
    {
      "@id": "https://elucidate.dlcs-ida.org/anno/a8fcac4c8fade2166792f64062d815b2/43",
      "@type": "oa:Annotation",
      "motivation": "sc:painting",
      "on": "https://presley.dlcs-ida.org/iiif/idatest01/_roll_M-1011_079_cvs-892-967/canvas/c918#xywh=428,1706,916,63",
      "resource": {
        "@type": "cnt:ContentAsText",
        "chars": "Annual Report, plus additions to roll..... ",
        "format": "text/plain"
      }
    },
    {
      "@id": "https://elucidate.dlcs-ida.org/anno/a8fcac4c8fade2166792f64062d815b2/44",
      "@type": "oa:Annotation",
      "motivation": "sc:painting",
      "on": "https://presley.dlcs-ida.org/iiif/idatest01/_roll_M-1011_079_cvs-892-967/canvas/c918#xywh=316,1791,501,65",
      "resource": {
        "@type": "cnt:ContentAsText",
        "chars": "4. Deductions, total... ",
        "format": "text/plain"
      }
    },
    {
      "@id": "https://elucidate.dlcs-ida.org/anno/a8fcac4c8fade2166792f64062d815b2/45",
      "@type": "oa:Annotation",
      "motivation": "sc:painting",
      "on": "https://presley.dlcs-ida.org/iiif/idatest01/_roll_M-1011_079_cvs-892-967/canvas/c918#xywh=451,1835,980,60",
      "resource": {
        "@type": "cnt:ContentAsText",
        "chars": "4- a. Deaths during the year( April 1, 1932 to ",
        "format": "text/plain"
      }
    },
    {
      "@id": "https://elucidate.dlcs-ida.org/anno/a8fcac4c8fade2166792f64062d815b2/46",
      "@type": "oa:Annotation",
      "motivation": "sc:painting",
      "on": "https://presley.dlcs-ida.org/iiif/idatest01/_roll_M-1011_079_cvs-892-967/canvas/c918#xywh=586,1882,513,58",
      "resource": {
        "@type": "cnt:ContentAsText",
        "chars": "March 31, 1933, only)... ",
        "format": "text/plain"
      }
    },
    {
      "@id": "https://elucidate.dlcs-ida.org/anno/a8fcac4c8fade2166792f64062d815b2/47",
      "@type": "oa:Annotation",
      "motivation": "sc:painting",
      "on": "https://presley.dlcs-ida.org/iiif/idatest01/_roll_M-1011_079_cvs-892-967/canvas/c918#xywh=455,1932,648,47",
      "resource": {
        "@type": "cnt:ContentAsText",
        "chars": "4- b. All other causes......... ",
        "format": "text/plain"
      }
    },
    {
      "@id": "https://elucidate.dlcs-ida.org/anno/a8fcac4c8fade2166792f64062d815b2/48",
      "@type": "oa:Annotation",
      "motivation": "sc:painting",
      "on": "https://presley.dlcs-ida.org/iiif/idatest01/_roll_M-1011_079_cvs-892-967/canvas/c918#xywh=605,1966,825,61",
      "resource": {
        "@type": "cnt:ContentAsText",
        "chars": "4 – 6( 1). Because of illegal or wrongful ",
        "format": "text/plain"
      }
    },
    {
      "@id": "https://elucidate.dlcs-ida.org/anno/a8fcac4c8fade2166792f64062d815b2/49",
      "@type": "oa:Annotation",
      "motivation": "sc:painting",
      "on": "https://presley.dlcs-ida.org/iiif/idatest01/_roll_M-1011_079_cvs-892-967/canvas/c918#xywh=800,2010,564,58",
      "resource": {
        "@type": "cnt:ContentAsText",
        "chars": "enrollment by Departmental ",
        "format": "text/plain"
      }
    },
    {
      "@id": "https://elucidate.dlcs-ida.org/anno/a8fcac4c8fade2166792f64062d815b2/50",
      "@type": "oa:Annotation",
      "motivation": "sc:painting",
      "on": "https://presley.dlcs-ida.org/iiif/idatest01/_roll_M-1011_079_cvs-892-967/canvas/c918#xywh=797,2059,414,53",
      "resource": {
        "@type": "cnt:ContentAsText",
        "chars": "authority.......... ",
        "format": "text/plain"
      }
    },
    {
      "@id": "https://elucidate.dlcs-ida.org/anno/a8fcac4c8fade2166792f64062d815b2/51",
      "@type": "oa:Annotation",
      "motivation": "sc:painting",
      "on": "https://presley.dlcs-ida.org/iiif/idatest01/_roll_M-1011_079_cvs-892-967/canvas/c918#xywh=603,2098,868,62",
      "resource": {
        "@type": "cnt:ContentAsText",
        "chars": "4- 6( 2). Deaths unreported, but occurring ",
        "format": "text/plain"
      }
    },
    {
      "@id": "https://elucidate.dlcs-ida.org/anno/a8fcac4c8fade2166792f64062d815b2/52",
      "@type": "oa:Annotation",
      "motivation": "sc:painting",
      "on": "https://presley.dlcs-ida.org/iiif/idatest01/_roll_M-1011_079_cvs-892-967/canvas/c918#xywh=801,2145,545,52",
      "resource": {
        "@type": "cnt:ContentAsText",
        "chars": "prior to April 1, 1932... ",
        "format": "text/plain"
      }
    },
    {
      "@id": "https://elucidate.dlcs-ida.org/anno/a8fcac4c8fade2166792f64062d815b2/53",
      "@type": "oa:Annotation",
      "motivation": "sc:painting",
      "on": "https://presley.dlcs-ida.org/iiif/idatest01/_roll_M-1011_079_cvs-892-967/canvas/c918#xywh=604,2190,788,54",
      "resource": {
        "@type": "cnt:ContentAsText",
        "chars": "4- 6( 3). Duplicat cas................ ",
        "format": "text/plain"
      }
    },
    {
      "@id": "https://elucidate.dlcs-ida.org/anno/a8fcac4c8fade2166792f64062d815b2/54",
      "@type": "oa:Annotation",
      "motivation": "sc:painting",
      "on": "https://presley.dlcs-ida.org/iiif/idatest01/_roll_M-1011_079_cvs-892-967/canvas/c918#xywh=604,2223,825,69",
      "resource": {
        "@type": "cnt:ContentAsText",
        "chars": "4- 6( 4). Because of error in sex....... ",
        "format": "text/plain"
      }
    },
    {
      "@id": "https://elucidate.dlcs-ida.org/anno/a8fcac4c8fade2166792f64062d815b2/55",
      "@type": "oa:Annotation",
      "motivation": "sc:painting",
      "on": "https://presley.dlcs-ida.org/iiif/idatest01/_roll_M-1011_079_cvs-892-967/canvas/c918#xywh=321,2409,1181,56",
      "resource": {
        "@type": "cnt:ContentAsText",
        "chars": "5. Total this Census( Sinciii. agree with last number on ",
        "format": "text/plain"
      }
    },
    {
      "@id": "https://elucidate.dlcs-ida.org/anno/a8fcac4c8fade2166792f64062d815b2/56",
      "@type": "oa:Annotation",
      "motivation": "sc:painting",
      "on": "https://presley.dlcs-ida.org/iiif/idatest01/_roll_M-1011_079_cvs-892-967/canvas/c918#xywh=430,2445,1135,69",
      "resource": {
        "@type": "cnt:ContentAsText",
        "chars": "current roll for the total for the reservation only. ",
        "format": "text/plain"
      }
    },
    {
      "@id": "https://elucidate.dlcs-ida.org/anno/a8fcac4c8fade2166792f64062d815b2/57",
      "@type": "oa:Annotation",
      "motivation": "sc:painting",
      "on": "https://presley.dlcs-ida.org/iiif/idatest01/_roll_M-1011_079_cvs-892-967/canvas/c918#xywh=429,2494,1118,63",
      "resource": {
        "@type": "cnt:ContentAsText",
        "chars": "Separate tribes, of course, can not clieck.)( Please ",
        "format": "text/plain"
      }
    },
    {
      "@id": "https://elucidate.dlcs-ida.org/anno/a8fcac4c8fade2166792f64062d815b2/58",
      "@type": "oa:Annotation",
      "motivation": "sc:painting",
      "on": "https://presley.dlcs-ida.org/iiif/idatest01/_roll_M-1011_079_cvs-892-967/canvas/c918#xywh=431,2537,1285,68",
      "resource": {
        "@type": "cnt:ContentAsText",
        "chars": "read instructions on back of sheets 17, 18, and 19.). 1865. ",
        "format": "text/plain"
      }
    },
    {
      "@id": "https://elucidate.dlcs-ida.org/anno/a8fcac4c8fade2166792f64062d815b2/59",
      "@type": "oa:Annotation",
      "motivation": "sc:painting",
      "on": "https://presley.dlcs-ida.org/iiif/idatest01/_roll_M-1011_079_cvs-892-967/canvas/c918#xywh=1385,2509,726,88",
      "resource": {
        "@type": "cnt:ContentAsText",
        "chars": "and 19.). 1865- 935- 930 ",
        "format": "text/plain"
      }
    },
    {
      "@id": "https://elucidate.dlcs-ida.org/anno/a8fcac4c8fade2166792f64062d815b2/60",
      "@type": "oa:Annotation",
      "motivation": "sc:painting",
      "on": "https://presley.dlcs-ida.org/iiif/idatest01/_roll_M-1011_079_cvs-892-967/canvas/c918#xywh=1808,2532,94,57",
      "resource": {
        "@type": "cnt:ContentAsText",
        "chars": "935. ",
        "format": "text/plain"
      }
    },
    {
      "@id": "https://elucidate.dlcs-ida.org/anno/a8fcac4c8fade2166792f64062d815b2/61",
      "@type": "oa:Annotation",
      "motivation": "sc:painting",
      "on": "https://presley.dlcs-ida.org/iiif/idatest01/_roll_M-1011_079_cvs-892-967/canvas/c918#xywh=2049,2536,84,44",
      "resource": {
        "@type": "cnt:ContentAsText",
        "chars": "930. ",
        "format": "text/plain"
      }
    },
    {
      "@id": "https://elucidate.dlcs-ida.org/anno/a8fcac4c8fade2166792f64062d815b2/62",
      "@type": "oa:Annotation",
      "motivation": "sc:painting",
      "on": "https://presley.dlcs-ida.org/iiif/idatest01/_roll_M-1011_079_cvs-892-967/canvas/c918#xywh=1193,2630,49,53",
      "resource": {
        "@type": "cnt:ContentAsText",
        "chars": "15 ",
        "format": "text/plain"
      }
    },
    {
      "@id": "https://elucidate.dlcs-ida.org/anno/a8fcac4c8fade2166792f64062d815b2/63",
      "@type": "oa:Annotation",
      "motivation": "sc:painting",
      "on": "https://presley.dlcs-ida.org/iiif/idatest01/_roll_M-1011_079_cvs-892-967/canvas/c918#xywh=1154,2719,124,54",
      "resource": {
        "@type": "cnt:ContentAsText",
        "chars": "( over) ",
        "format": "text/plain"
      }
    }
  ]
}